{
"meta":{"test_sets":[],"test_metrics":[],"learn_metrics":[{"best_value":"Min","name":"RMSE"}],"launch_mode":"Train","parameters":"","iteration_count":1000,"learn_sets":["learn"],"name":"experiment"},
"iterations":[
{"learn":[3.174751051],"iteration":0,"passed_time":0.1306161409,"remaining_time":130.4855248},
{"learn":[3.103106161],"iteration":1,"passed_time":0.1337698966,"remaining_time":66.75117842},
{"learn":[3.037466108],"iteration":2,"passed_time":0.1370989139,"remaining_time":45.56253905},
{"learn":[2.980281487],"iteration":3,"passed_time":0.1454827198,"remaining_time":36.22519722},
{"learn":[2.909895315],"iteration":4,"passed_time":0.1498004764,"remaining_time":29.81029481},
{"learn":[2.84190232],"iteration":5,"passed_time":0.1535425119,"remaining_time":25.43687613},
{"learn":[2.78357814],"iteration":6,"passed_time":0.1578118887,"remaining_time":22.38674364},
{"learn":[2.731755455],"iteration":7,"passed_time":0.1611649927,"remaining_time":19.9844591},
{"learn":[2.677097568],"iteration":8,"passed_time":0.1653680307,"remaining_time":18.2088576},
{"learn":[2.630851746],"iteration":9,"passed_time":0.1691004744,"remaining_time":16.74094696},
{"learn":[2.579778159],"iteration":10,"passed_time":0.1729534725,"remaining_time":15.55008948},
{"learn":[2.526122466],"iteration":11,"passed_time":0.1759588393,"remaining_time":14.48727777},
{"learn":[2.476894581],"iteration":12,"passed_time":0.1792417953,"remaining_time":13.60858861},
{"learn":[2.431054168],"iteration":13,"passed_time":0.1881071752,"remaining_time":13.24811963},
{"learn":[2.383703769],"iteration":14,"passed_time":0.1929668464,"remaining_time":12.67148958},
{"learn":[2.340789025],"iteration":15,"passed_time":0.1973781625,"remaining_time":12.13875699},
{"learn":[2.294876153],"iteration":16,"passed_time":0.200682557,"remaining_time":11.60417374},
{"learn":[2.25118114],"iteration":17,"passed_time":0.2040646604,"remaining_time":11.13286091},
{"learn":[2.210634987],"iteration":18,"passed_time":0.2083055585,"remaining_time":10.75514489},
{"learn":[2.171541314],"iteration":19,"passed_time":0.212579874,"remaining_time":10.41641383},
{"learn":[2.125494441],"iteration":20,"passed_time":0.216225062,"remaining_time":10.08020646},
{"learn":[2.090956199],"iteration":21,"passed_time":0.2191875396,"remaining_time":9.743882441},
{"learn":[2.053200776],"iteration":22,"passed_time":0.2222641071,"remaining_time":9.441392722},
{"learn":[2.021487024],"iteration":23,"passed_time":0.2289344183,"remaining_time":9.309999676},
{"learn":[1.988882221],"iteration":24,"passed_time":0.2345238362,"remaining_time":9.14642961},
{"learn":[1.9540189],"iteration":25,"passed_time":0.2400827977,"remaining_time":8.993870962},
{"learn":[1.926971238],"iteration":26,"passed_time":0.2432943912,"remaining_time":8.767608987},
{"learn":[1.893356418],"iteration":27,"passed_time":0.2463145112,"remaining_time":8.550632318},
{"learn":[1.866845679],"iteration":28,"passed_time":0.254357616,"remaining_time":8.516594661},
{"learn":[1.840585419],"iteration":29,"passed_time":0.2575888661,"remaining_time":8.328706671},
{"learn":[1.816245175],"iteration":30,"passed_time":0.2613681883,"remaining_time":8.169863691},
{"learn":[1.79097423],"iteration":31,"passed_time":0.2647183775,"remaining_time":8.00773092},
{"learn":[1.767187087],"iteration":32,"passed_time":0.2682345745,"remaining_time":7.860085865},
{"learn":[1.743882728],"iteration":33,"passed_time":0.2779692445,"remaining_time":7.897596771},
{"learn":[1.720187011],"iteration":34,"passed_time":0.2827199438,"remaining_time":7.794992735},
{"learn":[1.695689191],"iteration":35,"passed_time":0.288056836,"remaining_time":7.713521943},
{"learn":[1.677398237],"iteration":36,"passed_time":0.2911470792,"remaining_time":7.5776929},
{"learn":[1.655557659],"iteration":37,"passed_time":0.2948553812,"remaining_time":7.464496755},
{"learn":[1.6313608],"iteration":38,"passed_time":0.3020020469,"remaining_time":7.441640181},
{"learn":[1.610399811],"iteration":39,"passed_time":0.3055889275,"remaining_time":7.334134259},
{"learn":[1.593482709],"iteration":40,"passed_time":0.3091491308,"remaining_time":7.231073573},
{"learn":[1.577522635],"iteration":41,"passed_time":0.3121637365,"remaining_time":7.120306181},
{"learn":[1.559874471],"iteration":42,"passed_time":0.3155781496,"remaining_time":7.023448585},
{"learn":[1.544168396],"iteration":43,"passed_time":0.3190980411,"remaining_time":6.933130166},
{"learn":[1.53094462],"iteration":44,"passed_time":0.3307068715,"remaining_time":7.018334717},
{"learn":[1.512529709],"iteration":45,"passed_time":0.3377683861,"remaining_time":7.005022615},
{"learn":[1.497292458],"iteration":46,"passed_time":0.3514064519,"remaining_time":7.125326567},
{"learn":[1.481725386],"iteration":47,"passed_time":0.355044157,"remaining_time":7.041709114},
{"learn":[1.466903354],"iteration":48,"passed_time":0.3590064699,"remaining_time":6.967656181},
{"learn":[1.448250002],"iteration":49,"passed_time":0.3636586772,"remaining_time":6.909514867},
{"learn":[1.435663724],"iteration":50,"passed_time":0.3699252087,"remaining_time":6.883510256},
{"learn":[1.421992027],"iteration":51,"passed_time":0.3738653605,"remaining_time":6.815853111},
{"learn":[1.409837514],"iteration":52,"passed_time":0.3771628347,"remaining_time":6.739117066},
{"learn":[1.39594149],"iteration":53,"passed_time":0.380833481,"remaining_time":6.67163839},
{"learn":[1.382874061],"iteration":54,"passed_time":0.3838522199,"remaining_time":6.595279051},
{"learn":[1.369896642],"iteration":55,"passed_time":0.387278324,"remaining_time":6.528406034},
{"learn":[1.357873826],"iteration":56,"passed_time":0.3956723731,"remaining_time":6.545948208},
{"learn":[1.348934251],"iteration":57,"passed_time":0.3990193449,"remaining_time":6.480624533},
{"learn":[1.336830032],"iteration":58,"passed_time":0.4029830175,"remaining_time":6.427237618},
{"learn":[1.327736311],"iteration":59,"passed_time":0.4062973273,"remaining_time":6.365324794},
{"learn":[1.315977737],"iteration":60,"passed_time":0.4099564365,"remaining_time":6.310640883},
{"learn":[1.306643855],"iteration":61,"passed_time":0.4134107506,"remaining_time":6.254504581},
{"learn":[1.297483364],"iteration":62,"passed_time":0.4210252955,"remaining_time":6.261915903},
{"learn":[1.286567944],"iteration":63,"passed_time":0.4241445245,"remaining_time":6.203113671},
{"learn":[1.277345676],"iteration":64,"passed_time":0.4270458366,"remaining_time":6.142890111},
{"learn":[1.268366808],"iteration":65,"passed_time":0.4302178722,"remaining_time":6.088234737},
{"learn":[1.258893614],"iteration":66,"passed_time":0.4332390471,"remaining_time":6.033015387},
{"learn":[1.251606306],"iteration":67,"passed_time":0.4354421887,"remaining_time":5.96811941},
{"learn":[1.239304913],"iteration":68,"passed_time":0.4416232481,"remaining_time":5.958713681},
{"learn":[1.232019337],"iteration":69,"passed_time":0.4449963511,"remaining_time":5.912094379},
{"learn":[1.224981135],"iteration":70,"passed_time":0.4476074806,"remaining_time":5.856723232},
{"learn":[1.217707468],"iteration":71,"passed_time":0.4510032173,"remaining_time":5.812930357},
{"learn":[1.211137845],"iteration":72,"passed_time":0.4541855463,"remaining_time":5.767534267},
{"learn":[1.202650854],"iteration":73,"passed_time":0.4572741402,"remaining_time":5.722106133},
{"learn":[1.197767774],"iteration":74,"passed_time":0.4589021009,"remaining_time":5.659792577},
{"learn":[1.18908746],"iteration":75,"passed_time":0.4616740103,"remaining_time":5.61298402},
{"learn":[1.182866066],"iteration":76,"passed_time":0.4675536143,"remaining_time":5.604571247},
{"learn":[1.174630507],"iteration":77,"passed_time":0.4711172427,"remaining_time":5.568847407},
{"learn":[1.169919558],"iteration":78,"passed_time":0.475200328,"remaining_time":5.539993698},
{"learn":[1.161766203],"iteration":79,"passed_time":0.4787534407,"remaining_time":5.505664568},
{"learn":[1.156385168],"iteration":80,"passed_time":0.4822726022,"remaining_time":5.471710141},
{"learn":[1.150576867],"iteration":81,"passed_time":0.4868490848,"remaining_time":5.450334876},
{"learn":[1.145122335],"iteration":82,"passed_time":0.4915121114,"remaining_time":5.430320556},
{"learn":[1.1389862],"iteration":83,"passed_time":0.4950071669,"remaining_time":5.397935296},
{"learn":[1.135146731],"iteration":84,"passed_time":0.4986557965,"remaining_time":5.367882986},
{"learn":[1.130811266],"iteration":85,"passed_time":0.5024042803,"remaining_time":5.339505956},
{"learn":[1.127897122],"iteration":86,"passed_time":0.5049888687,"remaining_time":5.299480887},
{"learn":[1.120274933],"iteration":87,"passed_time":0.5126580305,"remaining_time":5.313001407},
{"learn":[1.116746454],"iteration":88,"passed_time":0.5164223338,"remaining_time":5.286075799},
{"learn":[1.112498556],"iteration":89,"passed_time":0.5195391495,"remaining_time":5.253118067},
{"learn":[1.106699905],"iteration":90,"passed_time":0.5232169925,"remaining_time":5.226420288},
{"learn":[1.102509377],"iteration":91,"passed_time":0.5263838247,"remaining_time":5.195179488},
{"learn":[1.097546096],"iteration":92,"passed_time":0.5295890326,"remaining_time":5.164916694},
{"learn":[1.091287532],"iteration":93,"passed_time":0.536151817,"remaining_time":5.167590917},
{"learn":[1.085595735],"iteration":94,"passed_time":0.5391880814,"remaining_time":5.136475933},
{"learn":[1.079198434],"iteration":95,"passed_time":0.5424307543,"remaining_time":5.107889603},
{"learn":[1.074266215],"iteration":96,"passed_time":0.5451896562,"remaining_time":5.075322263},
{"learn":[1.068046624],"iteration":97,"passed_time":0.5481969783,"remaining_time":5.045649739},
{"learn":[1.064891592],"iteration":98,"passed_time":0.5514851883,"remaining_time":5.019072269},
{"learn":[1.062321316],"iteration":99,"passed_time":0.5550843787,"remaining_time":4.995759409},
{"learn":[1.059548531],"iteration":100,"passed_time":0.5604454869,"remaining_time":4.98851973},
{"learn":[1.055206628],"iteration":101,"passed_time":0.5633280394,"remaining_time":4.959495876},
{"learn":[1.049103605],"iteration":102,"passed_time":0.5662296219,"remaining_time":4.931145348},
{"learn":[1.04574475],"iteration":103,"passed_time":0.5692369048,"remaining_time":4.904194872},
{"learn":[1.040714495],"iteration":104,"passed_time":0.5722070689,"remaining_time":4.877384063},
{"learn":[1.037996181],"iteration":105,"passed_time":0.5753201525,"remaining_time":4.852228456},
{"learn":[1.035130693],"iteration":106,"passed_time":0.5786492683,"remaining_time":4.829287819},
{"learn":[1.031605232],"iteration":107,"passed_time":0.583824771,"remaining_time":4.821960146},
{"learn":[1.025918628],"iteration":108,"passed_time":0.5870502421,"remaining_time":4.798731795},
{"learn":[1.022350373],"iteration":109,"passed_time":0.5900506374,"remaining_time":4.774046066},
{"learn":[1.017695513],"iteration":110,"passed_time":0.5943530691,"remaining_time":4.760179085},
{"learn":[1.013208582],"iteration":111,"passed_time":0.5992644166,"remaining_time":4.751310732},
{"learn":[1.008639748],"iteration":112,"passed_time":0.6030502705,"remaining_time":4.733677787},
{"learn":[1.003455719],"iteration":113,"passed_time":0.6084427917,"remaining_time":4.72877468},
{"learn":[0.9981210632],"iteration":114,"passed_time":0.6118385939,"remaining_time":4.708497005},
{"learn":[0.9945796325],"iteration":115,"passed_time":0.6178026225,"remaining_time":4.708082054},
{"learn":[0.9905517607],"iteration":116,"passed_time":0.6222795125,"remaining_time":4.696348799},
{"learn":[0.9864637904],"iteration":117,"passed_time":0.626283742,"remaining_time":4.681205597},
{"learn":[0.9807820391],"iteration":118,"passed_time":0.6314312252,"remaining_time":4.674713525},
{"learn":[0.9744570978],"iteration":119,"passed_time":0.6347591828,"remaining_time":4.654900674},
{"learn":[0.9709896825],"iteration":120,"passed_time":0.6400431254,"remaining_time":4.649569481},
{"learn":[0.9672416242],"iteration":121,"passed_time":0.6433732425,"remaining_time":4.630177925},
{"learn":[0.9650709826],"iteration":122,"passed_time":0.6474604453,"remaining_time":4.616445614},
{"learn":[0.9594251691],"iteration":123,"passed_time":0.6523075808,"remaining_time":4.608237426},
{"learn":[0.9553168274],"iteration":124,"passed_time":0.657841477,"remaining_time":4.604890339},
{"learn":[0.9531089067],"iteration":125,"passed_time":0.661351874,"remaining_time":4.587472523},
{"learn":[0.9484262304],"iteration":126,"passed_time":0.6655671844,"remaining_time":4.575119307},
{"learn":[0.9446173455],"iteration":127,"passed_time":0.6687122489,"remaining_time":4.555602196},
{"learn":[0.9415823829],"iteration":128,"passed_time":0.6720564158,"remaining_time":4.537683241},
{"learn":[0.9378007304],"iteration":129,"passed_time":0.677172513,"remaining_time":4.531846818},
{"learn":[0.9337073696],"iteration":130,"passed_time":0.6813867671,"remaining_time":4.520038936},
{"learn":[0.9303500927],"iteration":131,"passed_time":0.6849056173,"remaining_time":4.503773301},
{"learn":[0.9261380718],"iteration":132,"passed_time":0.6878315098,"remaining_time":4.483833977},
{"learn":[0.9249815077],"iteration":133,"passed_time":0.6909639662,"remaining_time":4.465483543},
{"learn":[0.9210725248],"iteration":134,"passed_time":0.6953792807,"remaining_time":4.455578354},
{"learn":[0.9164024285],"iteration":135,"passed_time":0.6993571514,"remaining_time":4.442974844},
{"learn":[0.911711441],"iteration":136,"passed_time":0.7040548269,"remaining_time":4.435031501},
{"learn":[0.9099931095],"iteration":137,"passed_time":0.7077932868,"remaining_time":4.421143574},
{"learn":[0.9079219557],"iteration":138,"passed_time":0.7121175805,"remaining_time":4.41103048},
{"learn":[0.9062859],"iteration":139,"passed_time":0.7163479724,"remaining_time":4.400423259},
{"learn":[0.9034380196],"iteration":140,"passed_time":0.7205328386,"remaining_time":4.389629138},
{"learn":[0.9015840955],"iteration":141,"passed_time":0.725645687,"remaining_time":4.384535207},
{"learn":[0.8968760036],"iteration":142,"passed_time":0.7295635478,"remaining_time":4.372279444},
{"learn":[0.8955984386],"iteration":143,"passed_time":0.7334816118,"remaining_time":4.360140692},
{"learn":[0.891884503],"iteration":144,"passed_time":0.7382541494,"remaining_time":4.353153778},
{"learn":[0.888450137],"iteration":145,"passed_time":0.7420078576,"remaining_time":4.340237742},
{"learn":[0.8853734921],"iteration":146,"passed_time":0.7469748489,"remaining_time":4.334486708},
{"learn":[0.8821534947],"iteration":147,"passed_time":0.7510945367,"remaining_time":4.323868549},
{"learn":[0.8787840453],"iteration":148,"passed_time":0.7564200802,"remaining_time":4.320224754},
{"learn":[0.8764683516],"iteration":149,"passed_time":0.7603542141,"remaining_time":4.30867388},
{"learn":[0.8733745287],"iteration":150,"passed_time":0.7650527259,"remaining_time":4.301521618},
{"learn":[0.8699626362],"iteration":151,"passed_time":0.7696352588,"remaining_time":4.293754602},
{"learn":[0.8670805181],"iteration":152,"passed_time":0.7734669933,"remaining_time":4.281872832},
{"learn":[0.86602112],"iteration":153,"passed_time":0.7766850631,"remaining_time":4.266724438},
{"learn":[0.8640254588],"iteration":154,"passed_time":0.7805905931,"remaining_time":4.25547775},
{"learn":[0.8626190036],"iteration":155,"passed_time":0.7858676212,"remaining_time":4.251745335},
{"learn":[0.860730708],"iteration":156,"passed_time":0.7930828437,"remaining_time":4.258400237},
{"learn":[0.8588448777],"iteration":157,"passed_time":0.7979859317,"remaining_time":4.25255794},
{"learn":[0.8566875776],"iteration":158,"passed_time":0.8017123992,"remaining_time":4.240503948},
{"learn":[0.8542322977],"iteration":159,"passed_time":0.8052673181,"remaining_time":4.22765342},
{"learn":[0.8513849548],"iteration":160,"passed_time":0.8088620666,"remaining_time":4.215125925},
{"learn":[0.8496444885],"iteration":161,"passed_time":0.8132472135,"remaining_time":4.206797314},
{"learn":[0.8486618811],"iteration":162,"passed_time":0.8178708257,"remaining_time":4.199741602},
{"learn":[0.8462841475],"iteration":163,"passed_time":0.8231687528,"remaining_time":4.19615291},
{"learn":[0.8441696688],"iteration":164,"passed_time":0.826701269,"remaining_time":4.183609452},
{"learn":[0.8405324656],"iteration":165,"passed_time":0.8329040124,"remaining_time":4.184590038},
{"learn":[0.8375748918],"iteration":166,"passed_time":0.8364616795,"remaining_time":4.172290892},
{"learn":[0.8363601191],"iteration":167,"passed_time":0.8415086028,"remaining_time":4.167471176},
{"learn":[0.8327541392],"iteration":168,"passed_time":0.8466170206,"remaining_time":4.162951148},
{"learn":[0.8309307528],"iteration":169,"passed_time":0.8505874786,"remaining_time":4.152868278},
{"learn":[0.8285557157],"iteration":170,"passed_time":0.8568525571,"remaining_time":4.15398111},
{"learn":[0.826865482],"iteration":171,"passed_time":0.8617731549,"remaining_time":4.148535885},
{"learn":[0.8257085741],"iteration":172,"passed_time":0.8701377049,"remaining_time":4.159560011},
{"learn":[0.8238131665],"iteration":173,"passed_time":0.8840390755,"remaining_time":4.196645267},
{"learn":[0.8225670178],"iteration":174,"passed_time":0.8938413364,"remaining_time":4.213823443},
{"learn":[0.8200471129],"iteration":175,"passed_time":0.9035114315,"remaining_time":4.230076248},
{"learn":[0.8177841956],"iteration":176,"passed_time":0.9091521602,"remaining_time":4.227300722},
{"learn":[0.8150492775],"iteration":177,"passed_time":0.9241240697,"remaining_time":4.267584187},
{"learn":[0.8133523894],"iteration":178,"passed_time":0.9287970374,"remaining_time":4.260013227},
{"learn":[0.8122435596],"iteration":179,"passed_time":0.9342608614,"remaining_time":4.256077258},
{"learn":[0.8107165335],"iteration":180,"passed_time":0.9474776029,"remaining_time":4.287205286},
{"learn":[0.808901451],"iteration":181,"passed_time":0.9575174024,"remaining_time":4.303567226},
{"learn":[0.8065546902],"iteration":182,"passed_time":0.9678391502,"remaining_time":4.320899376},
{"learn":[0.8034763356],"iteration":183,"passed_time":0.9766175204,"remaining_time":4.331086395},
{"learn":[0.8026571698],"iteration":184,"passed_time":0.9818008456,"remaining_time":4.325230752},
{"learn":[0.8010142851],"iteration":185,"passed_time":0.9873529763,"remaining_time":4.320996359},
{"learn":[0.8000200759],"iteration":186,"passed_time":0.9939352957,"remaining_time":4.321226713},
{"learn":[0.7992768734],"iteration":187,"passed_time":0.999955207,"remaining_time":4.318955469},
{"learn":[0.7982108759],"iteration":188,"passed_time":1.007430444,"remaining_time":4.322889364},
{"learn":[0.7968652152],"iteration":189,"passed_time":1.015676703,"remaining_time":4.329990157},
{"learn":[0.7948929143],"iteration":190,"passed_time":1.023110064,"remaining_time":4.333487131},
{"learn":[0.7932119741],"iteration":191,"passed_time":1.028148194,"remaining_time":4.326790318},
{"learn":[0.7907400635],"iteration":192,"passed_time":1.033490424,"remaining_time":4.321382241},
{"learn":[0.7871347165],"iteration":193,"passed_time":1.040753584,"remaining_time":4.323955613},
{"learn":[0.784482156],"iteration":194,"passed_time":1.050042122,"remaining_time":4.334789272},
{"learn":[0.7825632786],"iteration":195,"passed_time":1.057389333,"remaining_time":4.337454202},
{"learn":[0.7804586498],"iteration":196,"passed_time":1.06303918,"remaining_time":4.33309879},
{"learn":[0.7798287054],"iteration":197,"passed_time":1.068619859,"remaining_time":4.328450136},
{"learn":[0.77845419],"iteration":198,"passed_time":1.074002931,"remaining_time":4.322996722},
{"learn":[0.7767993514],"iteration":199,"passed_time":1.080303088,"remaining_time":4.321212353},
{"learn":[0.7751668657],"iteration":200,"passed_time":1.086036091,"remaining_time":4.317128542},
{"learn":[0.7736643693],"iteration":201,"passed_time":1.090546586,"remaining_time":4.308198889},
{"learn":[0.7714555673],"iteration":202,"passed_time":1.096244835,"remaining_time":4.303976026},
{"learn":[0.7708849701],"iteration":203,"passed_time":1.101668747,"remaining_time":4.298668249},
{"learn":[0.7696138288],"iteration":204,"passed_time":1.108680737,"remaining_time":4.299517979},
{"learn":[0.7683053969],"iteration":205,"passed_time":1.113496282,"remaining_time":4.291825475},
{"learn":[0.7672175449],"iteration":206,"passed_time":1.118414209,"remaining_time":4.284552985},
{"learn":[0.7652553298],"iteration":207,"passed_time":1.12326653,"remaining_time":4.277053325},
{"learn":[0.7643563782],"iteration":208,"passed_time":1.127823456,"remaining_time":4.268461021},
{"learn":[0.7634848706],"iteration":209,"passed_time":1.133608661,"remaining_time":4.264527819},
{"learn":[0.7601225452],"iteration":210,"passed_time":1.137154881,"remaining_time":4.252204746},
{"learn":[0.7587092517],"iteration":211,"passed_time":1.141382314,"remaining_time":4.242496526},
{"learn":[0.7577168022],"iteration":212,"passed_time":1.145155725,"remaining_time":4.231162231},
{"learn":[0.7565211418],"iteration":213,"passed_time":1.173161377,"remaining_time":4.308901132},
{"learn":[0.7544247041],"iteration":214,"passed_time":1.200857735,"remaining_time":4.384527078},
{"learn":[0.7536067559],"iteration":215,"passed_time":1.216489796,"remaining_time":4.415407407},
{"learn":[0.7529698327],"iteration":216,"passed_time":1.226773289,"remaining_time":4.426559838},
{"learn":[0.7502282645],"iteration":217,"passed_time":1.232329769,"remaining_time":4.420559079},
{"learn":[0.7495637356],"iteration":218,"passed_time":1.235811285,"remaining_time":4.407162618},
{"learn":[0.7481086043],"iteration":219,"passed_time":1.239451329,"remaining_time":4.39441835},
{"learn":[0.7475987927],"iteration":220,"passed_time":1.243601461,"remaining_time":4.383554469},
{"learn":[0.7466916978],"iteration":221,"passed_time":1.248591412,"remaining_time":4.375694227},
{"learn":[0.7450159262],"iteration":222,"passed_time":1.252940379,"remaining_time":4.365626344},
{"learn":[0.7430851387],"iteration":223,"passed_time":1.257035009,"remaining_time":4.354728423},
{"learn":[0.7399917986],"iteration":224,"passed_time":1.261439282,"remaining_time":4.344957528},
{"learn":[0.7388198762],"iteration":225,"passed_time":1.264988222,"remaining_time":4.332304794},
{"learn":[0.7359674947],"iteration":226,"passed_time":1.268669483,"remaining_time":4.320182864},
{"learn":[0.7354901747],"iteration":227,"passed_time":1.273585833,"remaining_time":4.312316943},
{"learn":[0.7339744844],"iteration":228,"passed_time":1.278151737,"remaining_time":4.303296896},
{"learn":[0.7332553945],"iteration":229,"passed_time":1.282280118,"remaining_time":4.292850829},
{"learn":[0.7305997885],"iteration":230,"passed_time":1.288311633,"remaining_time":4.288795005},
{"learn":[0.729257643],"iteration":231,"passed_time":1.2919713,"remaining_time":4.276870511},
{"learn":[0.7278480611],"iteration":232,"passed_time":1.297925233,"remaining_time":4.272569328},
{"learn":[0.72624041],"iteration":233,"passed_time":1.304138129,"remaining_time":4.269101738},
{"learn":[0.7254899949],"iteration":234,"passed_time":1.308683106,"remaining_time":4.260181175},
{"learn":[0.7232540118],"iteration":235,"passed_time":1.313141021,"remaining_time":4.251015848},
{"learn":[0.7218532649],"iteration":236,"passed_time":1.316893635,"remaining_time":4.239619591},
{"learn":[0.7208751759],"iteration":237,"passed_time":1.320989995,"remaining_time":4.229388136},
{"learn":[0.719602596],"iteration":238,"passed_time":1.332435167,"remaining_time":4.242607372},
{"learn":[0.716815873],"iteration":239,"passed_time":1.343595341,"remaining_time":4.254718578},
{"learn":[0.7146205066],"iteration":240,"passed_time":1.358784576,"remaining_time":4.279325696},
{"learn":[0.71308102],"iteration":241,"passed_time":1.366314032,"remaining_time":4.27961172},
{"learn":[0.711959357],"iteration":242,"passed_time":1.373466935,"remaining_time":4.27866037},
{"learn":[0.7108459019],"iteration":243,"passed_time":1.380258943,"remaining_time":4.276540002},
{"learn":[0.7092798501],"iteration":244,"passed_time":1.386652682,"remaining_time":4.273154184},
{"learn":[0.7080954361],"iteration":245,"passed_time":1.394125095,"remaining_time":4.273050087},
{"learn":[0.7062350717],"iteration":246,"passed_time":1.402233775,"remaining_time":4.274826044},
{"learn":[0.7053656618],"iteration":247,"passed_time":1.408066408,"remaining_time":4.269620722},
{"learn":[0.7039259475],"iteration":248,"passed_time":1.4126971,"remaining_time":4.260785229},
{"learn":[0.7023966834],"iteration":249,"passed_time":1.419938467,"remaining_time":4.2598154},
{"learn":[0.7015045967],"iteration":250,"passed_time":1.428030838,"remaining_time":4.261335049},
{"learn":[0.7000905265],"iteration":251,"passed_time":1.431976798,"remaining_time":4.250470813},
{"learn":[0.6988362078],"iteration":252,"passed_time":1.436281457,"remaining_time":4.24072035},
{"learn":[0.6984471846],"iteration":253,"passed_time":1.44153816,"remaining_time":4.233808927},
{"learn":[0.6971906473],"iteration":254,"passed_time":1.445616217,"remaining_time":4.223466986},
{"learn":[0.6962189045],"iteration":255,"passed_time":1.451510071,"remaining_time":4.218451144},
{"learn":[0.6958367576],"iteration":256,"passed_time":1.45620097,"remaining_time":4.209950663},
{"learn":[0.694520732],"iteration":257,"passed_time":1.461369403,"remaining_time":4.202853088},
{"learn":[0.6921846151],"iteration":258,"passed_time":1.466027364,"remaining_time":4.194309948},
{"learn":[0.690177843],"iteration":259,"passed_time":1.472432296,"remaining_time":4.190768842},
{"learn":[0.6887015067],"iteration":260,"passed_time":1.477984852,"remaining_time":4.18479236},
{"learn":[0.6874466896],"iteration":261,"passed_time":1.482664117,"remaining_time":4.17635923},
{"learn":[0.6857693148],"iteration":262,"passed_time":1.486873358,"remaining_time":4.166637509},
{"learn":[0.6845675032],"iteration":263,"passed_time":1.49050525,"remaining_time":4.155347969},
{"learn":[0.6824531318],"iteration":264,"passed_time":1.494583134,"remaining_time":4.145353221},
{"learn":[0.6799142605],"iteration":265,"passed_time":1.500265769,"remaining_time":4.139831107},
{"learn":[0.6771137312],"iteration":266,"passed_time":1.503694259,"remaining_time":4.128119444},
{"learn":[0.6762248731],"iteration":267,"passed_time":1.507721516,"remaining_time":4.118105037},
{"learn":[0.6755259321],"iteration":268,"passed_time":1.511171091,"remaining_time":4.106565308},
{"learn":[0.6731298505],"iteration":269,"passed_time":1.515654843,"remaining_time":4.097881612},
{"learn":[0.672565402],"iteration":270,"passed_time":1.520803539,"remaining_time":4.091017638},
{"learn":[0.671939769],"iteration":271,"passed_time":1.523880272,"remaining_time":4.078620729},
{"learn":[0.671385584],"iteration":272,"passed_time":1.527209296,"remaining_time":4.066963951},
{"learn":[0.6697714204],"iteration":273,"passed_time":1.531388792,"remaining_time":4.057621397},
{"learn":[0.6679545449],"iteration":274,"passed_time":1.536037001,"remaining_time":4.049552094},
{"learn":[0.6670190265],"iteration":275,"passed_time":1.539898542,"remaining_time":4.039444002},
{"learn":[0.6659255493],"iteration":276,"passed_time":1.545356231,"remaining_time":4.033547131},
{"learn":[0.66412664],"iteration":277,"passed_time":1.549354064,"remaining_time":4.023861995},
{"learn":[0.662990759],"iteration":278,"passed_time":1.557647472,"remaining_time":4.025318378},
{"learn":[0.6619109793],"iteration":279,"passed_time":1.560957549,"remaining_time":4.013890841},
{"learn":[0.6596934286],"iteration":280,"passed_time":1.564761675,"remaining_time":4.003785211},
{"learn":[0.6583067613],"iteration":281,"passed_time":1.570179893,"remaining_time":3.997833912},
{"learn":[0.6573423473],"iteration":282,"passed_time":1.573577115,"remaining_time":3.986766048},
{"learn":[0.6556891791],"iteration":283,"passed_time":1.577687791,"remaining_time":3.97755091},
{"learn":[0.6544570629],"iteration":284,"passed_time":1.581045859,"remaining_time":3.966483472},
{"learn":[0.6529375065],"iteration":285,"passed_time":1.584426688,"remaining_time":3.955526767},
{"learn":[0.6514745539],"iteration":286,"passed_time":1.594044419,"remaining_time":3.960117319},
{"learn":[0.6500238182],"iteration":287,"passed_time":1.597887447,"remaining_time":3.950332855},
{"learn":[0.6477008573],"iteration":288,"passed_time":1.602649097,"remaining_time":3.942849507},
{"learn":[0.6471151865],"iteration":289,"passed_time":1.606562641,"remaining_time":3.933308535},
{"learn":[0.645604534],"iteration":290,"passed_time":1.611948881,"remaining_time":3.927394352},
{"learn":[0.6438797551],"iteration":291,"passed_time":1.619144603,"remaining_time":3.925871161},
{"learn":[0.6427860054],"iteration":292,"passed_time":1.623524609,"remaining_time":3.917515011},
{"learn":[0.6417649176],"iteration":293,"passed_time":1.628896091,"remaining_time":3.911566804},
{"learn":[0.6390276857],"iteration":294,"passed_time":1.633817475,"remaining_time":3.904546847},
{"learn":[0.6377323259],"iteration":295,"passed_time":1.643207608,"remaining_time":3.908169445},
{"learn":[0.6371692566],"iteration":296,"passed_time":1.649203901,"remaining_time":3.903671186},
{"learn":[0.6368643598],"iteration":297,"passed_time":1.667007162,"remaining_time":3.926976602},
{"learn":[0.6362639468],"iteration":298,"passed_time":1.674681881,"remaining_time":3.926260865},
{"learn":[0.6347852879],"iteration":299,"passed_time":1.679393807,"remaining_time":3.918585549},
{"learn":[0.6342123546],"iteration":300,"passed_time":1.68873529,"remaining_time":3.921680955},
{"learn":[0.6327948404],"iteration":301,"passed_time":1.694295161,"remaining_time":3.915953716},
{"learn":[0.6314124633],"iteration":302,"passed_time":1.700690516,"remaining_time":3.91214947},
{"learn":[0.6301544695],"iteration":303,"passed_time":1.715381619,"remaining_time":3.927321074},
{"learn":[0.6292361238],"iteration":304,"passed_time":1.721651818,"remaining_time":3.92310824},
{"learn":[0.6286705502],"iteration":305,"passed_time":1.725305047,"remaining_time":3.912946741},
{"learn":[0.6285567304],"iteration":306,"passed_time":1.728588783,"remaining_time":3.901993572},
{"learn":[0.6272691122],"iteration":307,"passed_time":1.736869544,"remaining_time":3.902317287},
{"learn":[0.6259077788],"iteration":308,"passed_time":1.745234922,"remaining_time":3.902774534},
{"learn":[0.6251214294],"iteration":309,"passed_time":1.749482571,"remaining_time":3.894009592},
{"learn":[0.623760704],"iteration":310,"passed_time":1.759815591,"remaining_time":3.898755441},
{"learn":[0.6236875504],"iteration":311,"passed_time":1.765832538,"remaining_time":3.893887134},
{"learn":[0.6226703658],"iteration":312,"passed_time":1.771589049,"remaining_time":3.888439862},
{"learn":[0.6222414493],"iteration":313,"passed_time":1.776536294,"remaining_time":3.881222603},
{"learn":[0.6211286608],"iteration":314,"passed_time":1.783376659,"remaining_time":3.878136543},
{"learn":[0.6207639956],"iteration":315,"passed_time":1.788367921,"remaining_time":3.871024233},
{"learn":[0.6192460268],"iteration":316,"passed_time":1.799640113,"remaining_time":3.877458035},
{"learn":[0.6173812756],"iteration":317,"passed_time":1.807532405,"remaining_time":3.876531761},
{"learn":[0.6156882325],"iteration":318,"passed_time":1.813563376,"remaining_time":3.871588273},
{"learn":[0.6140947608],"iteration":319,"passed_time":1.819446148,"remaining_time":3.866323064},
{"learn":[0.6131406065],"iteration":320,"passed_time":1.825842794,"remaining_time":3.862140987},
{"learn":[0.6118157359],"iteration":321,"passed_time":1.834206043,"remaining_time":3.862086016},
{"learn":[0.6095374819],"iteration":322,"passed_time":1.846597715,"remaining_time":3.870423074},
{"learn":[0.6086258493],"iteration":323,"passed_time":1.852551162,"remaining_time":3.865199338},
{"learn":[0.6075678253],"iteration":324,"passed_time":1.85942099,"remaining_time":3.861874364},
{"learn":[0.605347296],"iteration":325,"passed_time":1.886861692,"remaining_time":3.901057609},
{"learn":[0.6038009863],"iteration":326,"passed_time":1.891466347,"remaining_time":3.892834408},
{"learn":[0.6037089343],"iteration":327,"passed_time":1.896063566,"remaining_time":3.884618038},
{"learn":[0.6028727315],"iteration":328,"passed_time":1.9067318,"remaining_time":3.888805586},
{"learn":[0.6013799899],"iteration":329,"passed_time":1.913047521,"remaining_time":3.88406618},
{"learn":[0.599530501],"iteration":330,"passed_time":1.920032996,"remaining_time":3.880670919},
{"learn":[0.5987071347],"iteration":331,"passed_time":1.931465904,"remaining_time":3.886202482},
{"learn":[0.5977324468],"iteration":332,"passed_time":1.942495643,"remaining_time":3.890824606},
{"learn":[0.5967218842],"iteration":333,"passed_time":1.947198023,"remaining_time":3.882736178},
{"learn":[0.5950144712],"iteration":334,"passed_time":1.966050403,"remaining_time":3.902756771},
{"learn":[0.5943303615],"iteration":335,"passed_time":1.970452322,"remaining_time":3.893989112},
{"learn":[0.5934623673],"iteration":336,"passed_time":1.994741438,"remaining_time":3.924372621},
{"learn":[0.5931359408],"iteration":337,"passed_time":2.000935048,"remaining_time":3.918991129},
{"learn":[0.5914436263],"iteration":338,"passed_time":2.005507029,"remaining_time":3.910442909},
{"learn":[0.5901690863],"iteration":339,"passed_time":2.010360839,"remaining_time":3.902465159},
{"learn":[0.5890922869],"iteration":340,"passed_time":2.014061253,"remaining_time":3.892276733},
{"learn":[0.5880289161],"iteration":341,"passed_time":2.017617761,"remaining_time":3.881849377},
{"learn":[0.5868841196],"iteration":342,"passed_time":2.022696527,"remaining_time":3.874377896},
{"learn":[0.5857634053],"iteration":343,"passed_time":2.030296661,"remaining_time":3.871728517},
{"learn":[0.5848572443],"iteration":344,"passed_time":2.035043021,"remaining_time":3.863632402},
{"learn":[0.5832363154],"iteration":345,"passed_time":2.039242172,"remaining_time":3.854521331},
{"learn":[0.5825696335],"iteration":346,"passed_time":2.04378837,"remaining_time":3.846091659},
{"learn":[0.5814218605],"iteration":347,"passed_time":2.049664173,"remaining_time":3.840175405},
{"learn":[0.5809684548],"iteration":348,"passed_time":2.054435422,"remaining_time":3.832199025},
{"learn":[0.5798285734],"iteration":349,"passed_time":2.058815875,"remaining_time":3.823515196},
{"learn":[0.5784856564],"iteration":350,"passed_time":2.06555321,"remaining_time":3.81921377},
{"learn":[0.5776474795],"iteration":351,"passed_time":2.074505322,"remaining_time":3.818975707},
{"learn":[0.5769472642],"iteration":352,"passed_time":2.079523636,"remaining_time":3.811478165},
{"learn":[0.5762149942],"iteration":353,"passed_time":2.084141447,"remaining_time":3.803263771},
{"learn":[0.57506172],"iteration":354,"passed_time":2.087604357,"remaining_time":3.792971296},
{"learn":[0.5741257146],"iteration":355,"passed_time":2.091003825,"remaining_time":3.782602425},
{"learn":[0.5732766546],"iteration":356,"passed_time":2.101091345,"remaining_time":3.784318585},
{"learn":[0.5721661547],"iteration":357,"passed_time":2.105507987,"remaining_time":3.775799239},
{"learn":[0.570884391],"iteration":358,"passed_time":2.109192911,"remaining_time":3.765996256},
{"learn":[0.5700919436],"iteration":359,"passed_time":2.112991985,"remaining_time":3.756430196},
{"learn":[0.5692532407],"iteration":360,"passed_time":2.118806004,"remaining_time":3.750462704},
{"learn":[0.5669605303],"iteration":361,"passed_time":2.124878195,"remaining_time":3.744951073},
{"learn":[0.5660249606],"iteration":362,"passed_time":2.129960141,"remaining_time":3.73769865},
{"learn":[0.5643858572],"iteration":363,"passed_time":2.134136163,"remaining_time":3.728875273},
{"learn":[0.5634606083],"iteration":364,"passed_time":2.137839015,"remaining_time":3.719254177},
{"learn":[0.5626416961],"iteration":365,"passed_time":2.152776736,"remaining_time":3.729126915},
{"learn":[0.561938471],"iteration":366,"passed_time":2.158023738,"remaining_time":3.722149935},
{"learn":[0.5608864695],"iteration":367,"passed_time":2.161312373,"remaining_time":3.711819075},
{"learn":[0.5599893595],"iteration":368,"passed_time":2.164245374,"remaining_time":3.700918242},
{"learn":[0.5591947502],"iteration":369,"passed_time":2.173142347,"remaining_time":3.700215348},
{"learn":[0.5576675863],"iteration":370,"passed_time":2.176234705,"remaining_time":3.689627034},
{"learn":[0.5571848112],"iteration":371,"passed_time":2.179959197,"remaining_time":3.680146172},
{"learn":[0.5555583756],"iteration":372,"passed_time":2.183236792,"remaining_time":3.669944956},
{"learn":[0.5544338554],"iteration":373,"passed_time":2.186498577,"remaining_time":3.659754303},
{"learn":[0.5522616946],"iteration":374,"passed_time":2.194135754,"remaining_time":3.656892923},
{"learn":[0.5504493128],"iteration":375,"passed_time":2.197347484,"remaining_time":3.646661781},
{"learn":[0.5490512197],"iteration":376,"passed_time":2.200988817,"remaining_time":3.637177806},
{"learn":[0.5481119223],"iteration":377,"passed_time":2.204882549,"remaining_time":3.628140067},
{"learn":[0.5465833308],"iteration":378,"passed_time":2.207991828,"remaining_time":3.61784413},
{"learn":[0.5458421231],"iteration":379,"passed_time":2.212264796,"remaining_time":3.609484667},
{"learn":[0.5442792422],"iteration":380,"passed_time":2.217070205,"remaining_time":3.602011698},
{"learn":[0.5439478701],"iteration":381,"passed_time":2.221144168,"remaining_time":3.593369361},
{"learn":[0.5430677486],"iteration":382,"passed_time":2.224519308,"remaining_time":3.5836251},
{"learn":[0.5426694336],"iteration":383,"passed_time":2.227771888,"remaining_time":3.573717403},
{"learn":[0.541295228],"iteration":384,"passed_time":2.230912439,"remaining_time":3.563665325},
{"learn":[0.5402978732],"iteration":385,"passed_time":2.244542936,"remaining_time":3.570335137},
{"learn":[0.5387328065],"iteration":386,"passed_time":2.249666648,"remaining_time":3.563425466},
{"learn":[0.5386850664],"iteration":387,"passed_time":2.25291544,"remaining_time":3.553567653},
{"learn":[0.5386295775],"iteration":388,"passed_time":2.255932556,"remaining_time":3.543379927},
{"learn":[0.5383972983],"iteration":389,"passed_time":2.267445229,"remaining_time":3.546516896},
{"learn":[0.5381868405],"iteration":390,"passed_time":2.27254192,"remaining_time":3.539585753},
{"learn":[0.536666689],"iteration":391,"passed_time":2.276558375,"remaining_time":3.530988499},
{"learn":[0.5359085279],"iteration":392,"passed_time":2.280898224,"remaining_time":3.522914051},
{"learn":[0.5349686397],"iteration":393,"passed_time":2.290154286,"remaining_time":3.522420043},
{"learn":[0.5342467613],"iteration":394,"passed_time":2.293439168,"remaining_time":3.512735941},
{"learn":[0.533376692],"iteration":395,"passed_time":2.29688787,"remaining_time":3.503334023},
{"learn":[0.5324345303],"iteration":396,"passed_time":2.300241251,"remaining_time":3.493817316},
{"learn":[0.5313114504],"iteration":397,"passed_time":2.303605149,"remaining_time":3.484347487},
{"learn":[0.5302625675],"iteration":398,"passed_time":2.308102452,"remaining_time":3.476615473},
{"learn":[0.529426479],"iteration":399,"passed_time":2.312538577,"remaining_time":3.468807865},
{"learn":[0.5285294557],"iteration":400,"passed_time":2.315955231,"remaining_time":3.459494223},
{"learn":[0.5276511025],"iteration":401,"passed_time":2.319228271,"remaining_time":3.449996284},
{"learn":[0.5263820929],"iteration":402,"passed_time":2.322522145,"remaining_time":3.440560101},
{"learn":[0.5256281441],"iteration":403,"passed_time":2.325629902,"remaining_time":3.430879757},
{"learn":[0.5247045704],"iteration":404,"passed_time":2.329015729,"remaining_time":3.421640392},
{"learn":[0.5246632949],"iteration":405,"passed_time":2.34624109,"remaining_time":3.432677851},
{"learn":[0.5238320841],"iteration":406,"passed_time":2.349293958,"remaining_time":3.422927069},
{"learn":[0.5229241168],"iteration":407,"passed_time":2.362874706,"remaining_time":3.428484867},
{"learn":[0.5221201752],"iteration":408,"passed_time":2.366490775,"remaining_time":3.419550239},
{"learn":[0.5212207879],"iteration":409,"passed_time":2.36991048,"remaining_time":3.410358983},
{"learn":[0.5205117739],"iteration":410,"passed_time":2.37332265,"remaining_time":3.401185014},
{"learn":[0.5199054133],"iteration":411,"passed_time":2.377618776,"remaining_time":3.393300584},
{"learn":[0.5188390572],"iteration":412,"passed_time":2.384058087,"remaining_time":3.388479654},
{"learn":[0.5171659093],"iteration":413,"passed_time":2.387466553,"remaining_time":3.37936087},
{"learn":[0.5160303233],"iteration":414,"passed_time":2.390659905,"remaining_time":3.369966372},
{"learn":[0.514810127],"iteration":415,"passed_time":2.395208748,"remaining_time":3.362504589},
{"learn":[0.5135748695],"iteration":416,"passed_time":2.399154334,"remaining_time":3.354213373},
{"learn":[0.5120974236],"iteration":417,"passed_time":2.403411836,"remaining_time":3.346377246},
{"learn":[0.5110362951],"iteration":418,"passed_time":2.409494963,"remaining_time":3.341089674},
{"learn":[0.5100601189],"iteration":419,"passed_time":2.413101275,"remaining_time":3.332377952},
{"learn":[0.5093666892],"iteration":420,"passed_time":2.416264433,"remaining_time":3.323081014},
{"learn":[0.5082242679],"iteration":421,"passed_time":2.419266667,"remaining_time":3.313592733},
{"learn":[0.5077735411],"iteration":422,"passed_time":2.422543735,"remaining_time":3.304510012},
{"learn":[0.5066185475],"iteration":423,"passed_time":2.426625322,"remaining_time":3.296547607},
{"learn":[0.5063930688],"iteration":424,"passed_time":2.43208769,"remaining_time":3.290471581},
{"learn":[0.5061285471],"iteration":425,"passed_time":2.435611226,"remaining_time":3.281786018},
{"learn":[0.505098608],"iteration":426,"passed_time":2.438577251,"remaining_time":3.272376499},
{"learn":[0.5044013039],"iteration":427,"passed_time":2.441751971,"remaining_time":3.263275998},
{"learn":[0.5034751697],"iteration":428,"passed_time":2.444994848,"remaining_time":3.254293842},
{"learn":[0.5027799585],"iteration":429,"passed_time":2.447879318,"remaining_time":3.244863282},
{"learn":[0.5027381168],"iteration":430,"passed_time":2.458035699,"remaining_time":3.24506337},
{"learn":[0.5020067441],"iteration":431,"passed_time":2.463075708,"remaining_time":3.238488432},
{"learn":[0.5012835491],"iteration":432,"passed_time":2.466401146,"remaining_time":3.229675404},
{"learn":[0.4994968477],"iteration":433,"passed_time":2.469621401,"remaining_time":3.220750491},
{"learn":[0.498215696],"iteration":434,"passed_time":2.472509676,"remaining_time":3.211420613},
{"learn":[0.4976345453],"iteration":435,"passed_time":2.482072576,"remaining_time":3.210754434},
{"learn":[0.495958465],"iteration":436,"passed_time":2.485189788,"remaining_time":3.201743365},
{"learn":[0.4946855859],"iteration":437,"passed_time":2.488622898,"remaining_time":3.19316454},
{"learn":[0.4940418078],"iteration":438,"passed_time":2.492140319,"remaining_time":3.184716899},
{"learn":[0.4938281129],"iteration":439,"passed_time":2.495170275,"remaining_time":3.175671259},
{"learn":[0.4928326004],"iteration":440,"passed_time":2.504779029,"remaining_time":3.174992012},
{"learn":[0.4921091549],"iteration":441,"passed_time":2.509247385,"remaining_time":3.167782898},
{"learn":[0.4917336208],"iteration":442,"passed_time":2.513013276,"remaining_time":3.159702922},
{"learn":[0.4908958887],"iteration":443,"passed_time":2.516149161,"remaining_time":3.150853454},
{"learn":[0.4901315134],"iteration":444,"passed_time":2.519254096,"remaining_time":3.141991063},
{"learn":[0.4892910913],"iteration":445,"passed_time":2.528128693,"remaining_time":3.140321291},
{"learn":[0.4881568765],"iteration":446,"passed_time":2.531444043,"remaining_time":3.131741735},
{"learn":[0.4873221823],"iteration":447,"passed_time":2.534432749,"remaining_time":3.122783208},
{"learn":[0.4861681092],"iteration":448,"passed_time":2.537630013,"remaining_time":3.11410721},
{"learn":[0.485248027],"iteration":449,"passed_time":2.541019843,"remaining_time":3.105690919},
{"learn":[0.4846630105],"iteration":450,"passed_time":2.544144835,"remaining_time":3.096974533},
{"learn":[0.4836008135],"iteration":451,"passed_time":2.550503817,"remaining_time":3.092203743},
{"learn":[0.4827554982],"iteration":452,"passed_time":2.554519191,"remaining_time":3.08459602},
{"learn":[0.4817510281],"iteration":453,"passed_time":2.559110125,"remaining_time":3.077696318},
{"learn":[0.480569551],"iteration":454,"passed_time":2.562567018,"remaining_time":3.069448406},
{"learn":[0.4799078153],"iteration":455,"passed_time":2.565791051,"remaining_time":3.060943709},
{"learn":[0.4797576178],"iteration":456,"passed_time":2.568816591,"remaining_time":3.052226277},
{"learn":[0.47930385],"iteration":457,"passed_time":2.574893604,"remaining_time":3.047144833},
{"learn":[0.4783543374],"iteration":458,"passed_time":2.578560242,"remaining_time":3.039218063},
{"learn":[0.4772591813],"iteration":459,"passed_time":2.582012923,"remaining_time":3.031058649},
{"learn":[0.4760021033],"iteration":460,"passed_time":2.586257132,"remaining_time":3.023845107},
{"learn":[0.474661476],"iteration":461,"passed_time":2.590085185,"remaining_time":3.016159805},
{"learn":[0.4740049162],"iteration":462,"passed_time":2.59975899,"remaining_time":3.015271226},
{"learn":[0.4728330688],"iteration":463,"passed_time":2.604819609,"remaining_time":3.009015755},
{"learn":[0.4717359972],"iteration":464,"passed_time":2.608981125,"remaining_time":3.001730972},
{"learn":[0.4710692947],"iteration":465,"passed_time":2.612313256,"remaining_time":2.993509182},
{"learn":[0.4710138658],"iteration":466,"passed_time":2.615459324,"remaining_time":2.985095973},
{"learn":[0.4695270751],"iteration":467,"passed_time":2.626900658,"remaining_time":2.986134937},
{"learn":[0.4685559913],"iteration":468,"passed_time":2.630583502,"remaining_time":2.978336545},
{"learn":[0.4673038661],"iteration":469,"passed_time":2.634322193,"remaining_time":2.970618643},
{"learn":[0.4672649018],"iteration":470,"passed_time":2.637838557,"remaining_time":2.962667933},
{"learn":[0.4664475628],"iteration":471,"passed_time":2.646992823,"remaining_time":2.961042819},
{"learn":[0.4657007287],"iteration":472,"passed_time":2.651044098,"remaining_time":2.953700295},
{"learn":[0.4646464571],"iteration":473,"passed_time":2.654806297,"remaining_time":2.94605087},
{"learn":[0.4639363003],"iteration":474,"passed_time":2.658590201,"remaining_time":2.938441801},
{"learn":[0.4630141953],"iteration":475,"passed_time":2.661715547,"remaining_time":2.930123837},
{"learn":[0.461993627],"iteration":476,"passed_time":2.672629485,"remaining_time":2.930367339},
{"learn":[0.4610137323],"iteration":477,"passed_time":2.67587095,"remaining_time":2.92218543},
{"learn":[0.459958612],"iteration":478,"passed_time":2.679638558,"remaining_time":2.914596428},
{"learn":[0.4589189041],"iteration":479,"passed_time":2.682573322,"remaining_time":2.906121099},
{"learn":[0.4580222215],"iteration":480,"passed_time":2.685539211,"remaining_time":2.897702392},
{"learn":[0.4577964413],"iteration":481,"passed_time":2.697954638,"remaining_time":2.899461624},
{"learn":[0.456837261],"iteration":482,"passed_time":2.702489233,"remaining_time":2.89272657},
{"learn":[0.4557139078],"iteration":483,"passed_time":2.706487295,"remaining_time":2.885428604},
{"learn":[0.4547172911],"iteration":484,"passed_time":2.709928016,"remaining_time":2.87755243},
{"learn":[0.4539251401],"iteration":485,"passed_time":2.722762665,"remaining_time":2.87962965},
{"learn":[0.4533236143],"iteration":486,"passed_time":2.727385678,"remaining_time":2.872995591},
{"learn":[0.4525457956],"iteration":487,"passed_time":2.730822992,"remaining_time":2.865125762},
{"learn":[0.4513015587],"iteration":488,"passed_time":2.734462466,"remaining_time":2.857485317},
{"learn":[0.4506361113],"iteration":489,"passed_time":2.748623535,"remaining_time":2.860812251},
{"learn":[0.4494485985],"iteration":490,"passed_time":2.751528578,"remaining_time":2.85239928},
{"learn":[0.4490560724],"iteration":491,"passed_time":2.755817502,"remaining_time":2.845437583},
{"learn":[0.4473583089],"iteration":492,"passed_time":2.759098158,"remaining_time":2.83744983},
{"learn":[0.4466894495],"iteration":493,"passed_time":2.766700274,"remaining_time":2.833907568},
{"learn":[0.4465974546],"iteration":494,"passed_time":2.771434863,"remaining_time":2.827423446},
{"learn":[0.4453900802],"iteration":495,"passed_time":2.775322331,"remaining_time":2.820085594},
{"learn":[0.4453543012],"iteration":496,"passed_time":2.864873974,"remaining_time":2.899459978},
{"learn":[0.4442430947],"iteration":497,"passed_time":2.87181579,"remaining_time":2.894882583},
{"learn":[0.4442038452],"iteration":498,"passed_time":2.877833188,"remaining_time":2.88936759},
{"learn":[0.4433940473],"iteration":499,"passed_time":2.885316101,"remaining_time":2.885316101},
{"learn":[0.4433703159],"iteration":500,"passed_time":2.892874803,"remaining_time":2.8813264},
{"learn":[0.4433428107],"iteration":501,"passed_time":2.944310286,"remaining_time":2.920849646},
{"learn":[0.4421175718],"iteration":502,"passed_time":2.997763761,"remaining_time":2.962005147},
{"learn":[0.4413916931],"iteration":503,"passed_time":3.012755717,"remaining_time":2.964934198},
{"learn":[0.440430437],"iteration":504,"passed_time":3.020905643,"remaining_time":2.961085729},
{"learn":[0.4392235476],"iteration":505,"passed_time":3.027389014,"remaining_time":2.955593227},
{"learn":[0.4381065136],"iteration":506,"passed_time":3.050789012,"remaining_time":2.966546317},
{"learn":[0.4369846043],"iteration":507,"passed_time":3.095814988,"remaining_time":2.998309004},
{"learn":[0.43624367],"iteration":508,"passed_time":3.102629624,"remaining_time":2.992909912},
{"learn":[0.4351216853],"iteration":509,"passed_time":3.116056913,"remaining_time":2.993858603},
{"learn":[0.4337567259],"iteration":510,"passed_time":3.120073121,"remaining_time":2.98574512},
{"learn":[0.4332563581],"iteration":511,"passed_time":3.124605331,"remaining_time":2.978139457},
{"learn":[0.4324200702],"iteration":512,"passed_time":3.128453945,"remaining_time":2.969896825},
{"learn":[0.4312280531],"iteration":513,"passed_time":3.197856072,"remaining_time":3.023653796},
{"learn":[0.4302279477],"iteration":514,"passed_time":3.202242684,"remaining_time":3.015704275},
{"learn":[0.429162795],"iteration":515,"passed_time":3.216957734,"remaining_time":3.017456479},
{"learn":[0.4281356895],"iteration":516,"passed_time":3.220429839,"remaining_time":3.008641416},
{"learn":[0.427149754],"iteration":517,"passed_time":3.223840929,"remaining_time":2.999790208},
{"learn":[0.4269967846],"iteration":518,"passed_time":3.22734713,"remaining_time":2.991048111},
{"learn":[0.4258501495],"iteration":519,"passed_time":3.242907997,"remaining_time":2.993453536},
{"learn":[0.4254579838],"iteration":520,"passed_time":3.246785514,"remaining_time":2.985048486},
{"learn":[0.4251140771],"iteration":521,"passed_time":3.250311278,"remaining_time":2.97633868},
{"learn":[0.4241997434],"iteration":522,"passed_time":3.260681651,"remaining_time":2.973891296},
{"learn":[0.4236268963],"iteration":523,"passed_time":3.264012466,"remaining_time":2.965018958},
{"learn":[0.4219597832],"iteration":524,"passed_time":3.266956156,"remaining_time":2.955817475},
{"learn":[0.4215456686],"iteration":525,"passed_time":3.270589971,"remaining_time":2.947261685},
{"learn":[0.4207870691],"iteration":526,"passed_time":3.273925373,"remaining_time":2.938456739},
{"learn":[0.4207633176],"iteration":527,"passed_time":3.28702384,"remaining_time":2.9384001},
{"learn":[0.4199339557],"iteration":528,"passed_time":3.290168349,"remaining_time":2.929431555},
{"learn":[0.4187430716],"iteration":529,"passed_time":3.293922444,"remaining_time":2.921025563},
{"learn":[0.4172100161],"iteration":530,"passed_time":3.297295059,"remaining_time":2.912300156},
{"learn":[0.416895089],"iteration":531,"passed_time":3.300591331,"remaining_time":2.903527712},
{"learn":[0.4160097477],"iteration":532,"passed_time":3.310198573,"remaining_time":2.900305317},
{"learn":[0.4151624369],"iteration":533,"passed_time":3.313514508,"remaining_time":2.89156884},
{"learn":[0.413987794],"iteration":534,"passed_time":3.316798067,"remaining_time":2.882824488},
{"learn":[0.4131217806],"iteration":535,"passed_time":3.319779308,"remaining_time":2.873838804},
{"learn":[0.4123852456],"iteration":536,"passed_time":3.323011397,"remaining_time":2.865091763},
{"learn":[0.4118427147],"iteration":537,"passed_time":3.334887324,"remaining_time":2.863788},
{"learn":[0.4114452345],"iteration":538,"passed_time":3.339234657,"remaining_time":2.856005894},
{"learn":[0.4109859258],"iteration":539,"passed_time":3.342784267,"remaining_time":2.847556968},
{"learn":[0.4103432791],"iteration":540,"passed_time":3.345936755,"remaining_time":2.838789225},
{"learn":[0.4095214286],"iteration":541,"passed_time":3.357745558,"remaining_time":2.837356947},
{"learn":[0.4088780151],"iteration":542,"passed_time":3.361443184,"remaining_time":2.829059917},
{"learn":[0.4077690473],"iteration":543,"passed_time":3.365163233,"remaining_time":2.820798592},
{"learn":[0.4076054748],"iteration":544,"passed_time":3.368309599,"remaining_time":2.812074986},
{"learn":[0.4065480294],"iteration":545,"passed_time":3.371847826,"remaining_time":2.803697643},
{"learn":[0.4059329679],"iteration":546,"passed_time":3.381930889,"remaining_time":2.800758122},
{"learn":[0.4051671674],"iteration":547,"passed_time":3.385333828,"remaining_time":2.792282646},
{"learn":[0.4049138191],"iteration":548,"passed_time":3.38854525,"remaining_time":2.78366832},
{"learn":[0.4047025451],"iteration":549,"passed_time":3.391616217,"remaining_time":2.774958723},
{"learn":[0.4041632053],"iteration":550,"passed_time":3.395136279,"remaining_time":2.766635552},
{"learn":[0.4041406783],"iteration":551,"passed_time":3.406171186,"remaining_time":2.764428789},
{"learn":[0.403508334],"iteration":552,"passed_time":3.41025959,"remaining_time":2.756575112},
{"learn":[0.4023911583],"iteration":553,"passed_time":3.413667445,"remaining_time":2.748187149},
{"learn":[0.4014320423],"iteration":554,"passed_time":3.417056194,"remaining_time":2.739801814},
{"learn":[0.4006620739],"iteration":555,"passed_time":3.420261861,"remaining_time":2.731288248},
{"learn":[0.3995244478],"iteration":556,"passed_time":3.431620022,"remaining_time":2.729277683},
{"learn":[0.3989750397],"iteration":557,"passed_time":3.437420505,"remaining_time":2.722831296},
{"learn":[0.3981767366],"iteration":558,"passed_time":3.440580371,"remaining_time":2.714304013},
{"learn":[0.3970819282],"iteration":559,"passed_time":3.444187665,"remaining_time":2.706147451},
{"learn":[0.3960639088],"iteration":560,"passed_time":3.454940598,"remaining_time":2.703598792},
{"learn":[0.3960441605],"iteration":561,"passed_time":3.458352303,"remaining_time":2.695299482},
{"learn":[0.3960241325],"iteration":562,"passed_time":3.461909877,"remaining_time":2.687130757},
{"learn":[0.3958684994],"iteration":563,"passed_time":3.464946684,"remaining_time":2.678575806},
{"learn":[0.3949294466],"iteration":564,"passed_time":3.468241541,"remaining_time":2.670239063},
{"learn":[0.3949056043],"iteration":565,"passed_time":3.481618837,"remaining_time":2.669651193},
{"learn":[0.3942922927],"iteration":566,"passed_time":3.484577469,"remaining_time":2.661061806},
{"learn":[0.3933503425],"iteration":567,"passed_time":3.487771745,"remaining_time":2.652671468},
{"learn":[0.3925349222],"iteration":568,"passed_time":3.491524004,"remaining_time":2.644722049},
{"learn":[0.3918124811],"iteration":569,"passed_time":3.504914646,"remaining_time":2.644058417},
{"learn":[0.3912733001],"iteration":570,"passed_time":3.507866971,"remaining_time":2.635507759},
{"learn":[0.3909314934],"iteration":571,"passed_time":3.511615984,"remaining_time":2.627572799},
{"learn":[0.3909083703],"iteration":572,"passed_time":3.514862257,"remaining_time":2.619277808},
{"learn":[0.3901234499],"iteration":573,"passed_time":3.532692436,"remaining_time":2.621824003},
{"learn":[0.3900699263],"iteration":574,"passed_time":3.537682892,"remaining_time":2.614809094},
{"learn":[0.3891173273],"iteration":575,"passed_time":3.541492297,"remaining_time":2.60693183},
{"learn":[0.3887364875],"iteration":576,"passed_time":3.548126495,"remaining_time":2.601139528},
{"learn":[0.387948226],"iteration":577,"passed_time":3.552953078,"remaining_time":2.594024566},
{"learn":[0.3873576921],"iteration":578,"passed_time":3.556429275,"remaining_time":2.585935621},
{"learn":[0.3864668937],"iteration":579,"passed_time":3.567690019,"remaining_time":2.583499669},
{"learn":[0.385688722],"iteration":580,"passed_time":3.572215854,"remaining_time":2.576176321},
{"learn":[0.3853589074],"iteration":581,"passed_time":3.576291622,"remaining_time":2.568539343},
{"learn":[0.3853050767],"iteration":582,"passed_time":3.579734223,"remaining_time":2.5604617},
{"learn":[0.3845037485],"iteration":583,"passed_time":3.597845508,"remaining_time":2.562848855},
{"learn":[0.3837516263],"iteration":584,"passed_time":3.601549789,"remaining_time":2.554945577},
{"learn":[0.3829209826],"iteration":585,"passed_time":3.604781026,"remaining_time":2.546722432},
{"learn":[0.3828980668],"iteration":586,"passed_time":3.621596395,"remaining_time":2.548073784},
{"learn":[0.3824302492],"iteration":587,"passed_time":3.624872699,"remaining_time":2.539876789},
{"learn":[0.3822841595],"iteration":588,"passed_time":3.629113541,"remaining_time":2.53236955},
{"learn":[0.3817169319],"iteration":589,"passed_time":3.649039599,"remaining_time":2.53577328},
{"learn":[0.3802188835],"iteration":590,"passed_time":3.652317449,"remaining_time":2.527576712},
{"learn":[0.3795430688],"iteration":591,"passed_time":3.661582385,"remaining_time":2.523522995},
{"learn":[0.3795212064],"iteration":592,"passed_time":3.665212972,"remaining_time":2.51558462},
{"learn":[0.3789302224],"iteration":593,"passed_time":3.669356636,"remaining_time":2.508011438},
{"learn":[0.3784929342],"iteration":594,"passed_time":3.67583813,"remaining_time":2.50204108},
{"learn":[0.3778353493],"iteration":595,"passed_time":3.685939854,"remaining_time":2.498522988},
{"learn":[0.3773507282],"iteration":596,"passed_time":3.68948199,"remaining_time":2.490554844},
{"learn":[0.3767954701],"iteration":597,"passed_time":3.693201619,"remaining_time":2.482720821},
{"learn":[0.376336419],"iteration":598,"passed_time":3.697214521,"remaining_time":2.475096866},
{"learn":[0.3758496029],"iteration":599,"passed_time":3.700616875,"remaining_time":2.467077917},
{"learn":[0.3748020904],"iteration":600,"passed_time":3.710981069,"remaining_time":2.46369625},
{"learn":[0.3736609277],"iteration":601,"passed_time":3.715035189,"remaining_time":2.45611961},
{"learn":[0.3736464118],"iteration":602,"passed_time":3.7178935,"remaining_time":2.447767362},
{"learn":[0.3736325059],"iteration":603,"passed_time":3.720808044,"remaining_time":2.439470174},
{"learn":[0.3729484346],"iteration":604,"passed_time":3.724755316,"remaining_time":2.431865041},
{"learn":[0.3720824408],"iteration":605,"passed_time":3.733891468,"remaining_time":2.427645608},
{"learn":[0.3714459902],"iteration":606,"passed_time":3.737318275,"remaining_time":2.41971348},
{"learn":[0.3708331349],"iteration":607,"passed_time":3.740783505,"remaining_time":2.411820944},
{"learn":[0.3700122276],"iteration":608,"passed_time":3.743902779,"remaining_time":2.403720832},
{"learn":[0.3693382952],"iteration":609,"passed_time":3.747315984,"remaining_time":2.395824973},
{"learn":[0.3687713021],"iteration":610,"passed_time":3.757413665,"remaining_time":2.392199535},
{"learn":[0.3683733602],"iteration":611,"passed_time":3.761394215,"remaining_time":2.384674764},
{"learn":[0.3676467089],"iteration":612,"passed_time":3.765635217,"remaining_time":2.377325985},
{"learn":[0.3668715847],"iteration":613,"passed_time":3.770095782,"remaining_time":2.370125361},
{"learn":[0.3661651898],"iteration":614,"passed_time":3.776328945,"remaining_time":2.364043323},
{"learn":[0.3654619132],"iteration":615,"passed_time":3.779582977,"remaining_time":2.356103674},
{"learn":[0.3649941543],"iteration":616,"passed_time":3.783396258,"remaining_time":2.348526365},
{"learn":[0.3638056704],"iteration":617,"passed_time":3.787633639,"remaining_time":2.341223382},
{"learn":[0.3629145582],"iteration":618,"passed_time":3.791331806,"remaining_time":2.333598414},
{"learn":[0.3624092973],"iteration":619,"passed_time":3.794953801,"remaining_time":2.325939427},
{"learn":[0.3617356085],"iteration":620,"passed_time":3.804970172,"remaining_time":2.322195966},
{"learn":[0.3613308519],"iteration":621,"passed_time":3.808554607,"remaining_time":2.314523539},
{"learn":[0.3608252492],"iteration":622,"passed_time":3.812309159,"remaining_time":2.30696718},
{"learn":[0.3603643301],"iteration":623,"passed_time":3.817364226,"remaining_time":2.300206649},
{"learn":[0.3596624055],"iteration":624,"passed_time":3.826079916,"remaining_time":2.295647949},
{"learn":[0.3588470168],"iteration":625,"passed_time":3.830652866,"remaining_time":2.288600913},
{"learn":[0.3583709672],"iteration":626,"passed_time":3.836339766,"remaining_time":2.282224454},
{"learn":[0.3579186883],"iteration":627,"passed_time":3.840374909,"remaining_time":2.274871762},
{"learn":[0.3574547821],"iteration":628,"passed_time":3.843584193,"remaining_time":2.267042505},
{"learn":[0.3568489168],"iteration":629,"passed_time":3.857890009,"remaining_time":2.265744926},
{"learn":[0.3563580523],"iteration":630,"passed_time":3.865482408,"remaining_time":2.260480204},
{"learn":[0.3559201984],"iteration":631,"passed_time":3.8769185,"remaining_time":2.257446215},
{"learn":[0.3547982203],"iteration":632,"passed_time":3.881583364,"remaining_time":2.250459865},
{"learn":[0.3542171364],"iteration":633,"passed_time":3.886256531,"remaining_time":2.243485632},
{"learn":[0.3535747069],"iteration":634,"passed_time":3.890421178,"remaining_time":2.236226346},
{"learn":[0.3532832855],"iteration":635,"passed_time":3.901600724,"remaining_time":2.232991609},
{"learn":[0.3530040115],"iteration":636,"passed_time":3.906004282,"remaining_time":2.225870572},
{"learn":[0.3519500471],"iteration":637,"passed_time":3.909967675,"remaining_time":2.218508305},
{"learn":[0.3512466546],"iteration":638,"passed_time":3.913296444,"remaining_time":2.210798148},
{"learn":[0.3506358491],"iteration":639,"passed_time":3.916940787,"remaining_time":2.203279193},
{"learn":[0.3500087672],"iteration":640,"passed_time":3.922053423,"remaining_time":2.196594663},
{"learn":[0.3495966689],"iteration":641,"passed_time":3.926853659,"remaining_time":2.189740825},
{"learn":[0.3489254038],"iteration":642,"passed_time":3.932487526,"remaining_time":2.183356216},
{"learn":[0.3478746375],"iteration":643,"passed_time":3.935851015,"remaining_time":2.175718884},
{"learn":[0.3471760705],"iteration":644,"passed_time":3.942960716,"remaining_time":2.170156673},
{"learn":[0.346536958],"iteration":645,"passed_time":3.94695792,"remaining_time":2.162884062},
{"learn":[0.3455699916],"iteration":646,"passed_time":3.952771613,"remaining_time":2.156612642},
{"learn":[0.3455532687],"iteration":647,"passed_time":3.955633274,"remaining_time":2.148739062},
{"learn":[0.344669941],"iteration":648,"passed_time":3.958695478,"remaining_time":2.140989388},
{"learn":[0.3442266442],"iteration":649,"passed_time":3.964017834,"remaining_time":2.134471141},
{"learn":[0.3437205536],"iteration":650,"passed_time":3.969509004,"remaining_time":2.12804707},
{"learn":[0.3433678183],"iteration":651,"passed_time":3.973559372,"remaining_time":2.120856843},
{"learn":[0.3430308666],"iteration":652,"passed_time":3.977738348,"remaining_time":2.113744574},
{"learn":[0.3423988267],"iteration":653,"passed_time":3.981728627,"remaining_time":2.106541445},
{"learn":[0.3417696641],"iteration":654,"passed_time":3.987246725,"remaining_time":2.100152855},
{"learn":[0.3416186811],"iteration":655,"passed_time":3.991810818,"remaining_time":2.093266649},
{"learn":[0.3408118792],"iteration":656,"passed_time":3.996437423,"remaining_time":2.086420146},
{"learn":[0.3404410528],"iteration":657,"passed_time":4.000153752,"remaining_time":2.07910727},
{"learn":[0.3399071706],"iteration":658,"passed_time":4.004099652,"remaining_time":2.071924099},
{"learn":[0.3394574341],"iteration":659,"passed_time":4.007772342,"remaining_time":2.064609994},
{"learn":[0.3391764565],"iteration":660,"passed_time":4.012690522,"remaining_time":2.057945669},
{"learn":[0.3391365467],"iteration":661,"passed_time":4.016394065,"remaining_time":2.050666456},
{"learn":[0.3383117629],"iteration":662,"passed_time":4.019564462,"remaining_time":2.043127034},
{"learn":[0.3382971916],"iteration":663,"passed_time":4.022917015,"remaining_time":2.035692947},
{"learn":[0.3375801811],"iteration":664,"passed_time":4.025941882,"remaining_time":2.028106061},
{"learn":[0.3367498875],"iteration":665,"passed_time":4.029750894,"remaining_time":2.020926124},
{"learn":[0.3360269488],"iteration":666,"passed_time":4.036825913,"remaining_time":2.01538685},
{"learn":[0.3356173451],"iteration":667,"passed_time":4.040326929,"remaining_time":2.008066678},
{"learn":[0.3349450438],"iteration":668,"passed_time":4.043560368,"remaining_time":2.000625533},
{"learn":[0.3343649773],"iteration":669,"passed_time":4.047197645,"remaining_time":1.993395855},
{"learn":[0.3337980837],"iteration":670,"passed_time":4.050212512,"remaining_time":1.985871708},
{"learn":[0.3326229836],"iteration":671,"passed_time":4.053735874,"remaining_time":1.978609177},
{"learn":[0.3322077861],"iteration":672,"passed_time":4.058470029,"remaining_time":1.971946062},
{"learn":[0.3318619643],"iteration":673,"passed_time":4.0623533,"remaining_time":1.964877115},
{"learn":[0.3313567133],"iteration":674,"passed_time":4.066202564,"remaining_time":1.957801235},
{"learn":[0.3304114494],"iteration":675,"passed_time":4.070898031,"remaining_time":1.951140477},
{"learn":[0.3296237182],"iteration":676,"passed_time":4.076083412,"remaining_time":1.944719265},
{"learn":[0.3288349205],"iteration":677,"passed_time":4.081540801,"remaining_time":1.938430882},
{"learn":[0.3286401336],"iteration":678,"passed_time":4.085822478,"remaining_time":1.931589124},
{"learn":[0.3282466035],"iteration":679,"passed_time":4.09001597,"remaining_time":1.924713398},
{"learn":[0.3282427915],"iteration":680,"passed_time":4.09391734,"remaining_time":1.91770871},
{"learn":[0.3282319772],"iteration":681,"passed_time":4.098359951,"remaining_time":1.91096549},
{"learn":[0.3272861438],"iteration":682,"passed_time":4.10294751,"remaining_time":1.904296282},
{"learn":[0.3266974461],"iteration":683,"passed_time":4.108271984,"remaining_time":1.897973607},
{"learn":[0.3259720261],"iteration":684,"passed_time":4.112024134,"remaining_time":1.890930806},
{"learn":[0.3253014561],"iteration":685,"passed_time":4.124158833,"remaining_time":1.88773451},
{"learn":[0.324471262],"iteration":686,"passed_time":4.220667314,"remaining_time":1.92295323},
{"learn":[0.3239012865],"iteration":687,"passed_time":4.444402074,"remaining_time":2.015484662},
{"learn":[0.3231587314],"iteration":688,"passed_time":4.460046991,"remaining_time":2.013170703},
{"learn":[0.3228408496],"iteration":689,"passed_time":4.468777873,"remaining_time":2.007711798},
{"learn":[0.3220680185],"iteration":690,"passed_time":4.486996506,"remaining_time":2.006486137},
{"learn":[0.3214945673],"iteration":691,"passed_time":4.498874712,"remaining_time":2.002389323},
{"learn":[0.3209159083],"iteration":692,"passed_time":4.51146221,"remaining_time":1.998584269},
{"learn":[0.3203840554],"iteration":693,"passed_time":4.518254834,"remaining_time":1.992198817},
{"learn":[0.3196111978],"iteration":694,"passed_time":4.539092845,"remaining_time":1.991975997},
{"learn":[0.3193028591],"iteration":695,"passed_time":4.551877961,"remaining_time":1.988176581},
{"learn":[0.3186662134],"iteration":696,"passed_time":4.556685034,"remaining_time":1.980883164},
{"learn":[0.3181635286],"iteration":697,"passed_time":4.561830036,"remaining_time":1.973743081},
{"learn":[0.3181541217],"iteration":698,"passed_time":4.575946094,"remaining_time":1.97047178},
{"learn":[0.3177185868],"iteration":699,"passed_time":4.584408795,"remaining_time":1.964746627},
{"learn":[0.3172455033],"iteration":700,"passed_time":4.591029183,"remaining_time":1.958227854},
{"learn":[0.3165577273],"iteration":701,"passed_time":4.595313739,"remaining_time":1.950717228},
{"learn":[0.3158823263],"iteration":702,"passed_time":4.601148883,"remaining_time":1.943870865},
{"learn":[0.3152317821],"iteration":703,"passed_time":4.604945401,"remaining_time":1.936170225},
{"learn":[0.3149893836],"iteration":704,"passed_time":4.611384053,"remaining_time":1.929586235},
{"learn":[0.3143127828],"iteration":705,"passed_time":4.618712127,"remaining_time":1.923373039},
{"learn":[0.3137614333],"iteration":706,"passed_time":4.625671497,"remaining_time":1.917003888},
{"learn":[0.3134176682],"iteration":707,"passed_time":4.632717282,"remaining_time":1.91066871},
{"learn":[0.3127698304],"iteration":708,"passed_time":4.636207813,"remaining_time":1.902872318},
{"learn":[0.3120278649],"iteration":709,"passed_time":4.640498001,"remaining_time":1.895414676},
{"learn":[0.3113521437],"iteration":710,"passed_time":4.649080407,"remaining_time":1.889710601},
{"learn":[0.3108572035],"iteration":711,"passed_time":4.652869446,"remaining_time":1.882059551},
{"learn":[0.3103310194],"iteration":712,"passed_time":4.656821232,"remaining_time":1.874484844},
{"learn":[0.3096872196],"iteration":713,"passed_time":4.66115322,"remaining_time":1.867072578},
{"learn":[0.3092913572],"iteration":714,"passed_time":4.664883462,"remaining_time":1.859429072},
{"learn":[0.3088551632],"iteration":715,"passed_time":4.678609897,"remaining_time":1.855761468},
{"learn":[0.3081994929],"iteration":716,"passed_time":4.682464138,"remaining_time":1.848169248},
{"learn":[0.3073872331],"iteration":717,"passed_time":4.685632664,"remaining_time":1.840318121},
{"learn":[0.3067858043],"iteration":718,"passed_time":4.688843406,"remaining_time":1.832496519},
{"learn":[0.3064281095],"iteration":719,"passed_time":4.698220618,"remaining_time":1.827085796},
{"learn":[0.305958542],"iteration":720,"passed_time":4.704991887,"remaining_time":1.820655668},
{"learn":[0.3051219745],"iteration":721,"passed_time":4.713826014,"remaining_time":1.815018881},
{"learn":[0.3045650096],"iteration":722,"passed_time":4.728274156,"remaining_time":1.811524123},
{"learn":[0.3035202049],"iteration":723,"passed_time":4.732810268,"remaining_time":1.804220489},
{"learn":[0.3029663425],"iteration":724,"passed_time":4.737531624,"remaining_time":1.796994754},
{"learn":[0.3022080675],"iteration":725,"passed_time":4.761971655,"remaining_time":1.797217952},
{"learn":[0.3016115332],"iteration":726,"passed_time":4.765820005,"remaining_time":1.7896408},
{"learn":[0.3011895088],"iteration":727,"passed_time":4.772512556,"remaining_time":1.783136559},
{"learn":[0.3009515719],"iteration":728,"passed_time":4.778940768,"remaining_time":1.776533537},
{"learn":[0.3002392252],"iteration":729,"passed_time":4.782746678,"remaining_time":1.7689611},
{"learn":[0.2997149282],"iteration":730,"passed_time":4.787352818,"remaining_time":1.761693445},
{"learn":[0.2988650511],"iteration":731,"passed_time":4.801894578,"remaining_time":1.758070692},
{"learn":[0.2981511353],"iteration":732,"passed_time":4.809730328,"remaining_time":1.75197544},
{"learn":[0.2976614813],"iteration":733,"passed_time":4.818855024,"remaining_time":1.746342556},
{"learn":[0.2968004495],"iteration":734,"passed_time":4.827797379,"remaining_time":1.740634429},
{"learn":[0.2961024881],"iteration":735,"passed_time":4.833773473,"remaining_time":1.733853529},
{"learn":[0.2951136843],"iteration":736,"passed_time":4.86143612,"remaining_time":1.734813703},
{"learn":[0.2944878322],"iteration":737,"passed_time":4.873900563,"remaining_time":1.730300742},
{"learn":[0.2940295867],"iteration":738,"passed_time":4.881664207,"remaining_time":1.724106032},
{"learn":[0.2931328311],"iteration":739,"passed_time":4.895835211,"remaining_time":1.720158317},
{"learn":[0.2928970069],"iteration":740,"passed_time":4.905853018,"remaining_time":1.714731352},
{"learn":[0.2926859392],"iteration":741,"passed_time":4.909344273,"remaining_time":1.707022672},
{"learn":[0.2923831387],"iteration":742,"passed_time":4.919918282,"remaining_time":1.701775233},
{"learn":[0.2917201625],"iteration":743,"passed_time":4.925793849,"remaining_time":1.694896808},
{"learn":[0.2911699101],"iteration":744,"passed_time":4.930437593,"remaining_time":1.687599445},
{"learn":[0.2905413198],"iteration":745,"passed_time":4.936051721,"remaining_time":1.680639594},
{"learn":[0.2905373836],"iteration":746,"passed_time":4.943800831,"remaining_time":1.674406439},
{"learn":[0.2901292436],"iteration":747,"passed_time":4.949349097,"remaining_time":1.667427771},
{"learn":[0.2894932634],"iteration":748,"passed_time":4.954276546,"remaining_time":1.660244877},
{"learn":[0.2886914352],"iteration":749,"passed_time":4.963860169,"remaining_time":1.654620056},
{"learn":[0.2882918606],"iteration":750,"passed_time":4.97076682,"remaining_time":1.648097122},
{"learn":[0.2882132686],"iteration":751,"passed_time":4.975704927,"remaining_time":1.640923965},
{"learn":[0.2876055404],"iteration":752,"passed_time":4.98063045,"remaining_time":1.633752618},
{"learn":[0.2867748853],"iteration":753,"passed_time":4.987366339,"remaining_time":1.627177877},
{"learn":[0.2863641618],"iteration":754,"passed_time":4.992793803,"remaining_time":1.620178121},
{"learn":[0.2858351496],"iteration":755,"passed_time":4.999032277,"remaining_time":1.61344428},
{"learn":[0.2853919115],"iteration":756,"passed_time":5.003268684,"remaining_time":1.606069076},
{"learn":[0.2851676711],"iteration":757,"passed_time":5.010371287,"remaining_time":1.599617218},
{"learn":[0.2848014446],"iteration":758,"passed_time":5.015746307,"remaining_time":1.592615099},
{"learn":[0.2840078274],"iteration":759,"passed_time":5.020799107,"remaining_time":1.585515508},
{"learn":[0.2834974438],"iteration":760,"passed_time":5.025554003,"remaining_time":1.578327736},
{"learn":[0.2830616544],"iteration":761,"passed_time":5.039313275,"remaining_time":1.57395874},
{"learn":[0.2825378753],"iteration":762,"passed_time":5.053845407,"remaining_time":1.569805192},
{"learn":[0.2817071816],"iteration":763,"passed_time":5.100594004,"remaining_time":1.575576158},
{"learn":[0.2811972212],"iteration":764,"passed_time":5.118645858,"remaining_time":1.572394479},
{"learn":[0.2808843741],"iteration":765,"passed_time":5.124489652,"remaining_time":1.56544462},
{"learn":[0.2805622808],"iteration":766,"passed_time":5.132870048,"remaining_time":1.559268215},
{"learn":[0.2801567884],"iteration":767,"passed_time":5.138733692,"remaining_time":1.552325803},
{"learn":[0.2794624274],"iteration":768,"passed_time":5.144262662,"remaining_time":1.545285663},
{"learn":[0.2789943423],"iteration":769,"passed_time":5.148357334,"remaining_time":1.537821022},
{"learn":[0.2786712121],"iteration":770,"passed_time":5.159212903,"remaining_time":1.532373223},
{"learn":[0.2782633718],"iteration":771,"passed_time":5.165064697,"remaining_time":1.525433615},
{"learn":[0.2779888004],"iteration":772,"passed_time":5.1692993,"remaining_time":1.518021916},
{"learn":[0.2771780868],"iteration":773,"passed_time":5.173344398,"remaining_time":1.510563093},
{"learn":[0.2766918737],"iteration":774,"passed_time":5.184362277,"remaining_time":1.505137435},
{"learn":[0.2762318995],"iteration":775,"passed_time":5.187637375,"remaining_time":1.497462335},
{"learn":[0.2756845833],"iteration":776,"passed_time":5.191608248,"remaining_time":1.489998249},
{"learn":[0.2752626495],"iteration":777,"passed_time":5.195126114,"remaining_time":1.482413878},
{"learn":[0.2750855976],"iteration":778,"passed_time":5.203050047,"remaining_time":1.476089936},
{"learn":[0.2743914314],"iteration":779,"passed_time":5.208604746,"remaining_time":1.469093646},
{"learn":[0.2738432002],"iteration":780,"passed_time":5.214232302,"remaining_time":1.462121478},
{"learn":[0.273178932],"iteration":781,"passed_time":5.218253278,"remaining_time":1.454704878},
{"learn":[0.2728593587],"iteration":782,"passed_time":5.221895547,"remaining_time":1.447191997},
{"learn":[0.2725555909],"iteration":783,"passed_time":5.23589092,"remaining_time":1.442541376},
{"learn":[0.2719523555],"iteration":784,"passed_time":5.240488011,"remaining_time":1.435292895},
{"learn":[0.271724649],"iteration":785,"passed_time":5.265487922,"remaining_time":1.433606126},
{"learn":[0.2713774712],"iteration":786,"passed_time":5.269231316,"remaining_time":1.426107078},
{"learn":[0.2706793589],"iteration":787,"passed_time":5.286146274,"remaining_time":1.42216118},
{"learn":[0.2703602071],"iteration":788,"passed_time":5.290512749,"remaining_time":1.414826603},
{"learn":[0.2696837379],"iteration":789,"passed_time":5.294343551,"remaining_time":1.407357146},
{"learn":[0.2692507828],"iteration":790,"passed_time":5.310034521,"remaining_time":1.403030613},
{"learn":[0.2687881639],"iteration":791,"passed_time":5.31341288,"remaining_time":1.395441766},
{"learn":[0.2683512983],"iteration":792,"passed_time":5.317144219,"remaining_time":1.387955679},
{"learn":[0.2679238413],"iteration":793,"passed_time":5.334093046,"remaining_time":1.383908271},
{"learn":[0.2676007747],"iteration":794,"passed_time":5.337838186,"remaining_time":1.376423683},
{"learn":[0.2668675624],"iteration":795,"passed_time":5.342073987,"remaining_time":1.369074238},
{"learn":[0.2668640975],"iteration":796,"passed_time":5.349774582,"remaining_time":1.362615107},
{"learn":[0.2663221872],"iteration":797,"passed_time":5.356586921,"remaining_time":1.355928018},
{"learn":[0.265770708],"iteration":798,"passed_time":5.360373282,"remaining_time":1.348479386},
{"learn":[0.2652479922],"iteration":799,"passed_time":5.365362374,"remaining_time":1.341340594},
{"learn":[0.2648326388],"iteration":800,"passed_time":5.376119592,"remaining_time":1.335640198},
{"learn":[0.2643247321],"iteration":801,"passed_time":5.380735537,"remaining_time":1.328411018},
{"learn":[0.2636678646],"iteration":802,"passed_time":5.383994036,"remaining_time":1.320855324},
{"learn":[0.2632383964],"iteration":803,"passed_time":5.38717223,"remaining_time":1.313290743},
{"learn":[0.2627805432],"iteration":804,"passed_time":5.39002372,"remaining_time":1.30565792},
{"learn":[0.2623668579],"iteration":805,"passed_time":5.405409756,"remaining_time":1.301053961},
{"learn":[0.2617545616],"iteration":806,"passed_time":5.410182783,"remaining_time":1.293885102},
{"learn":[0.261205789],"iteration":807,"passed_time":5.413542061,"remaining_time":1.286386232},
{"learn":[0.2605995968],"iteration":808,"passed_time":5.425887836,"remaining_time":1.281019254},
{"learn":[0.2599875318],"iteration":809,"passed_time":5.429174206,"remaining_time":1.273509999},
{"learn":[0.2595899127],"iteration":810,"passed_time":5.432914907,"remaining_time":1.266117037},
{"learn":[0.2590631523],"iteration":811,"passed_time":5.436029956,"remaining_time":1.258588216},
{"learn":[0.2584429421],"iteration":812,"passed_time":5.439536163,"remaining_time":1.251160225},
{"learn":[0.2581481604],"iteration":813,"passed_time":5.44504248,"remaining_time":1.244198896},
{"learn":[0.2577694155],"iteration":814,"passed_time":5.448489013,"remaining_time":1.23677358},
{"learn":[0.2572307274],"iteration":815,"passed_time":5.452298057,"remaining_time":1.229439758},
{"learn":[0.256778739],"iteration":816,"passed_time":5.464172971,"remaining_time":1.223921241},
{"learn":[0.2563959946],"iteration":817,"passed_time":5.470082466,"remaining_time":1.217059913},
{"learn":[0.2558756917],"iteration":818,"passed_time":5.473882216,"remaining_time":1.209734653},
{"learn":[0.2550428201],"iteration":819,"passed_time":5.485552401,"remaining_time":1.204145649},
{"learn":[0.254313205],"iteration":820,"passed_time":5.493201407,"remaining_time":1.197665106},
{"learn":[0.2539326166],"iteration":821,"passed_time":5.498384133,"remaining_time":1.190647659},
{"learn":[0.25392337],"iteration":822,"passed_time":5.503712979,"remaining_time":1.183666096},
{"learn":[0.2531522156],"iteration":823,"passed_time":5.522542842,"remaining_time":1.179572257},
{"learn":[0.2528118441],"iteration":824,"passed_time":5.525996016,"remaining_time":1.172180973},
{"learn":[0.2523136352],"iteration":825,"passed_time":5.535742902,"remaining_time":1.166125018},
{"learn":[0.2515676216],"iteration":826,"passed_time":5.542345426,"remaining_time":1.159402368},
{"learn":[0.2512600263],"iteration":827,"passed_time":5.547501994,"remaining_time":1.152379641},
{"learn":[0.2505650659],"iteration":828,"passed_time":5.556878497,"remaining_time":1.146231873},
{"learn":[0.2500771162],"iteration":829,"passed_time":5.56073046,"remaining_time":1.138944793},
{"learn":[0.2491688306],"iteration":830,"passed_time":5.566045046,"remaining_time":1.131963433},
{"learn":[0.24860074],"iteration":831,"passed_time":5.570238819,"remaining_time":1.124759762},
{"learn":[0.2483788536],"iteration":832,"passed_time":5.573742151,"remaining_time":1.117424897},
{"learn":[0.2480127452],"iteration":833,"passed_time":5.584494971,"remaining_time":1.111542165},
{"learn":[0.2475830811],"iteration":834,"passed_time":5.588377866,"remaining_time":1.104290237},
{"learn":[0.2469345874],"iteration":835,"passed_time":5.592424092,"remaining_time":1.09707841},
{"learn":[0.2466030635],"iteration":836,"passed_time":5.596670397,"remaining_time":1.089913112},
{"learn":[0.2459084816],"iteration":837,"passed_time":5.605060549,"remaining_time":1.083555858},
{"learn":[0.2457209431],"iteration":838,"passed_time":5.610497,"remaining_time":1.076626957},
{"learn":[0.2453537001],"iteration":839,"passed_time":5.614873422,"remaining_time":1.069499699},
{"learn":[0.2447767537],"iteration":840,"passed_time":5.618422453,"remaining_time":1.062222557},
{"learn":[0.2444293255],"iteration":841,"passed_time":5.624549667,"remaining_time":1.055438061},
{"learn":[0.2439162345],"iteration":842,"passed_time":5.631979082,"remaining_time":1.048897646},
{"learn":[0.2433918685],"iteration":843,"passed_time":5.635904003,"remaining_time":1.041707375},
{"learn":[0.2425108593],"iteration":844,"passed_time":5.63979433,"remaining_time":1.034518487},
{"learn":[0.2420169101],"iteration":845,"passed_time":5.643469373,"remaining_time":1.027298207},
{"learn":[0.2416776376],"iteration":846,"passed_time":5.649840823,"remaining_time":1.020573372},
{"learn":[0.2412391785],"iteration":847,"passed_time":5.660651284,"remaining_time":1.014645041},
{"learn":[0.2410688663],"iteration":848,"passed_time":5.665579331,"remaining_time":1.007658986},
{"learn":[0.2410582064],"iteration":849,"passed_time":5.675189884,"remaining_time":1.001504097},
{"learn":[0.2409811898],"iteration":850,"passed_time":5.681959522,"remaining_time":0.9948436766},
{"learn":[0.2407522645],"iteration":851,"passed_time":5.688185032,"remaining_time":0.9880884798},
{"learn":[0.240399241],"iteration":852,"passed_time":5.703770664,"remaining_time":0.9829475822},
{"learn":[0.239830937],"iteration":853,"passed_time":5.710820457,"remaining_time":0.9763229352},
{"learn":[0.2395883412],"iteration":854,"passed_time":5.715882523,"remaining_time":0.9693601939},
{"learn":[0.2392513756],"iteration":855,"passed_time":5.724939557,"remaining_time":0.9630739441},
{"learn":[0.2387124419],"iteration":856,"passed_time":5.755517523,"remaining_time":0.9603722355},
{"learn":[0.2383230643],"iteration":857,"passed_time":5.762276612,"remaining_time":0.9536634952},
{"learn":[0.2379473996],"iteration":858,"passed_time":5.771120922,"remaining_time":0.9472969151},
{"learn":[0.2374607315],"iteration":859,"passed_time":5.778352809,"remaining_time":0.9406620853},
{"learn":[0.236987347],"iteration":860,"passed_time":5.784380884,"remaining_time":0.9338315248},
{"learn":[0.2366352581],"iteration":861,"passed_time":5.789298274,"remaining_time":0.9268250137},
{"learn":[0.2359966616],"iteration":862,"passed_time":5.795491037,"remaining_time":0.9200258077},
{"learn":[0.235394157],"iteration":863,"passed_time":5.799657857,"remaining_time":0.9129091071},
{"learn":[0.2350178289],"iteration":864,"passed_time":5.803599985,"remaining_time":0.9057641595},
{"learn":[0.2344450337],"iteration":865,"passed_time":5.807243413,"remaining_time":0.8985803895},
{"learn":[0.2343524657],"iteration":866,"passed_time":5.811375563,"remaining_time":0.8914797577},
{"learn":[0.2339487436],"iteration":867,"passed_time":5.817534105,"remaining_time":0.8846941265},
{"learn":[0.2339363924],"iteration":868,"passed_time":5.822767024,"remaining_time":0.8777704029},
{"learn":[0.2332074873],"iteration":869,"passed_time":5.826840637,"remaining_time":0.8706773366},
{"learn":[0.2327000102],"iteration":870,"passed_time":5.830872255,"remaining_time":0.8635849838},
{"learn":[0.2323658539],"iteration":871,"passed_time":5.834935185,"remaining_time":0.8565042473},
{"learn":[0.2320486922],"iteration":872,"passed_time":5.839881543,"remaining_time":0.8495589415},
{"learn":[0.2318044456],"iteration":873,"passed_time":5.845382483,"remaining_time":0.8426981612},
{"learn":[0.231292378],"iteration":874,"passed_time":5.848939314,"remaining_time":0.8355627592},
{"learn":[0.2309429779],"iteration":875,"passed_time":5.852504104,"remaining_time":0.8284366539},
{"learn":[0.2304181048],"iteration":876,"passed_time":5.856387891,"remaining_time":0.82136341},
{"learn":[0.2300792644],"iteration":877,"passed_time":5.860620349,"remaining_time":0.8143458799},
{"learn":[0.2296506976],"iteration":878,"passed_time":5.868150335,"remaining_time":0.8077886126},
{"learn":[0.2293213455],"iteration":879,"passed_time":5.875175854,"remaining_time":0.8011603437},
{"learn":[0.2289466989],"iteration":880,"passed_time":5.97420396,"remaining_time":0.8069583102},
{"learn":[0.2284814047],"iteration":881,"passed_time":5.982382356,"remaining_time":0.8003640794},
{"learn":[0.228080654],"iteration":882,"passed_time":5.992016514,"remaining_time":0.7939591531},
{"learn":[0.2276110412],"iteration":883,"passed_time":5.998061388,"remaining_time":0.7870759287},
{"learn":[0.227086047],"iteration":884,"passed_time":6.005074303,"remaining_time":0.7803203897},
{"learn":[0.2268339685],"iteration":885,"passed_time":6.009787819,"remaining_time":0.7732684101},
{"learn":[0.2263180285],"iteration":886,"passed_time":6.016733643,"remaining_time":0.7665060899},
{"learn":[0.2261607711],"iteration":887,"passed_time":6.025649556,"remaining_time":0.7599918359},
{"learn":[0.2257844066],"iteration":888,"passed_time":6.031194395,"remaining_time":0.7530512686},
{"learn":[0.2254222813],"iteration":889,"passed_time":6.038900393,"remaining_time":0.7463809475},
{"learn":[0.2252789796],"iteration":890,"passed_time":6.044554891,"remaining_time":0.7394573323},
{"learn":[0.2251559518],"iteration":891,"passed_time":6.20040928,"remaining_time":0.7507221998},
{"learn":[0.2248802887],"iteration":892,"passed_time":6.204837377,"remaining_time":0.7434687562},
{"learn":[0.2243991007],"iteration":893,"passed_time":6.213483537,"remaining_time":0.7367217617},
{"learn":[0.2241287621],"iteration":894,"passed_time":6.220561057,"remaining_time":0.7297864927},
{"learn":[0.2236313752],"iteration":895,"passed_time":6.224711274,"remaining_time":0.7225111301},
{"learn":[0.2231436198],"iteration":896,"passed_time":6.228796431,"remaining_time":0.7152352646},
{"learn":[0.2227653914],"iteration":897,"passed_time":6.235331111,"remaining_time":0.7082447364},
{"learn":[0.2222458021],"iteration":898,"passed_time":6.24025818,"remaining_time":0.701074612},
{"learn":[0.2222380236],"iteration":899,"passed_time":6.244185281,"remaining_time":0.6937983645},
{"learn":[0.2217423345],"iteration":900,"passed_time":6.247838966,"remaining_time":0.686499509},
{"learn":[0.2214224491],"iteration":901,"passed_time":6.252108622,"remaining_time":0.6792756596},
{"learn":[0.2214135161],"iteration":902,"passed_time":6.257388804,"remaining_time":0.6721669037},
{"learn":[0.220876103],"iteration":903,"passed_time":6.263147685,"remaining_time":0.6651130285},
{"learn":[0.2202308067],"iteration":904,"passed_time":6.26712569,"remaining_time":0.6578750724},
{"learn":[0.2197130016],"iteration":905,"passed_time":6.270734189,"remaining_time":0.6506059754},
{"learn":[0.219296142],"iteration":906,"passed_time":6.274381195,"remaining_time":0.6433488987},
{"learn":[0.2188750204],"iteration":907,"passed_time":6.277931388,"remaining_time":0.6360899644},
{"learn":[0.2186368852],"iteration":908,"passed_time":6.28636872,"remaining_time":0.6293284417},
{"learn":[0.2182309754],"iteration":909,"passed_time":6.291316923,"remaining_time":0.6222181572},
{"learn":[0.2178962721],"iteration":910,"passed_time":6.295086458,"remaining_time":0.6149974695},
{"learn":[0.2175789285],"iteration":911,"passed_time":6.298879071,"remaining_time":0.607786577},
{"learn":[0.2175689887],"iteration":912,"passed_time":6.302896199,"remaining_time":0.6006045666},
{"learn":[0.2170476091],"iteration":913,"passed_time":6.309936268,"remaining_time":0.5937139158},
{"learn":[0.216514098],"iteration":914,"passed_time":6.315495714,"remaining_time":0.5866853942},
{"learn":[0.2157805705],"iteration":915,"passed_time":6.319080684,"remaining_time":0.5794790147},
{"learn":[0.2152953049],"iteration":916,"passed_time":6.322880362,"remaining_time":0.5722999673},
{"learn":[0.2152921252],"iteration":917,"passed_time":6.327015023,"remaining_time":0.5651582047},
{"learn":[0.2149454802],"iteration":918,"passed_time":6.332685456,"remaining_time":0.5581583481},
{"learn":[0.2148910018],"iteration":919,"passed_time":6.336346223,"remaining_time":0.5509866281},
{"learn":[0.2145217137],"iteration":920,"passed_time":6.339905169,"remaining_time":0.5438137984},
{"learn":[0.2140999207],"iteration":921,"passed_time":6.343284104,"remaining_time":0.5366335793},
{"learn":[0.213652209],"iteration":922,"passed_time":6.34699576,"remaining_time":0.5294893537},
{"learn":[0.2133956915],"iteration":923,"passed_time":6.351282476,"remaining_time":0.5223998573},
{"learn":[0.2128459511],"iteration":924,"passed_time":6.355152601,"remaining_time":0.5152826433},
{"learn":[0.2123542415],"iteration":925,"passed_time":6.359372507,"remaining_time":0.5082003947},
{"learn":[0.2120250259],"iteration":926,"passed_time":6.362754707,"remaining_time":0.5010583534},
{"learn":[0.211607996],"iteration":927,"passed_time":6.36629399,"remaining_time":0.4939366027},
{"learn":[0.21128946],"iteration":928,"passed_time":6.37018406,"remaining_time":0.4868493738},
{"learn":[0.2108139809],"iteration":929,"passed_time":6.375742083,"remaining_time":0.4798945654},
{"learn":[0.2103990426],"iteration":930,"passed_time":6.380420586,"remaining_time":0.472877573},
{"learn":[0.2100358957],"iteration":931,"passed_time":6.385028722,"remaining_time":0.4658604647},
{"learn":[0.2097606396],"iteration":932,"passed_time":6.392590369,"remaining_time":0.459060616},
{"learn":[0.2092758916],"iteration":933,"passed_time":6.398001554,"remaining_time":0.4521071762},
{"learn":[0.2088200623],"iteration":934,"passed_time":6.404611027,"remaining_time":0.4452403388},
{"learn":[0.2083722923],"iteration":935,"passed_time":6.409803814,"remaining_time":0.4382771839},
{"learn":[0.2081962229],"iteration":936,"passed_time":6.414125081,"remaining_time":0.4312592103},
{"learn":[0.207701775],"iteration":937,"passed_time":6.417682519,"remaining_time":0.4241964991},
{"learn":[0.2075539554],"iteration":938,"passed_time":6.421963186,"remaining_time":0.4171882368},
{"learn":[0.2071055281],"iteration":939,"passed_time":6.428350577,"remaining_time":0.4103202496},
{"learn":[0.2066865835],"iteration":940,"passed_time":6.432710826,"remaining_time":0.4033261836},
{"learn":[0.2063425198],"iteration":941,"passed_time":6.436668778,"remaining_time":0.3963129396},
{"learn":[0.205787996],"iteration":942,"passed_time":6.440455189,"remaining_time":0.3892958067},
{"learn":[0.2054631214],"iteration":943,"passed_time":6.445235183,"remaining_time":0.38234446},
{"learn":[0.2051015254],"iteration":944,"passed_time":6.451166132,"remaining_time":0.3754646955},
{"learn":[0.2043584167],"iteration":945,"passed_time":6.45475269,"remaining_time":0.3684531134},
{"learn":[0.2041552891],"iteration":946,"passed_time":6.458991953,"remaining_time":0.3614852941},
{"learn":[0.2038446673],"iteration":947,"passed_time":6.463210349,"remaining_time":0.3545220866},
{"learn":[0.2034962787],"iteration":948,"passed_time":6.468107454,"remaining_time":0.3476011382},
{"learn":[0.203004844],"iteration":949,"passed_time":6.476521144,"remaining_time":0.3408695339},
{"learn":[0.2027395951],"iteration":950,"passed_time":6.482257444,"remaining_time":0.3339964403},
{"learn":[0.2022666843],"iteration":951,"passed_time":6.487085947,"remaining_time":0.3270799637},
{"learn":[0.2021744406],"iteration":952,"passed_time":6.490683921,"remaining_time":0.3201071819},
{"learn":[0.2019568758],"iteration":953,"passed_time":6.497850213,"remaining_time":0.3133135323},
{"learn":[0.2016794467],"iteration":954,"passed_time":6.502504805,"remaining_time":0.30640075},
{"learn":[0.2012110824],"iteration":955,"passed_time":6.506522268,"remaining_time":0.299463368},
{"learn":[0.2007450672],"iteration":956,"passed_time":6.510768948,"remaining_time":0.2925423874},
{"learn":[0.2004386786],"iteration":957,"passed_time":6.514779381,"remaining_time":0.2856166326},
{"learn":[0.2000305055],"iteration":958,"passed_time":6.520042413,"remaining_time":0.2787505099},
{"learn":[0.1998508147],"iteration":959,"passed_time":6.524634487,"remaining_time":0.2718597703},
{"learn":[0.1995315182],"iteration":960,"passed_time":6.528718925,"remaining_time":0.2649532134},
{"learn":[0.1992042507],"iteration":961,"passed_time":6.532449817,"remaining_time":0.2580385583},
{"learn":[0.199051786],"iteration":962,"passed_time":6.536524813,"remaining_time":0.2511437363},
{"learn":[0.1987275366],"iteration":963,"passed_time":6.542369355,"remaining_time":0.2443208473},
{"learn":[0.1984210429],"iteration":964,"passed_time":6.546466579,"remaining_time":0.2374366117},
{"learn":[0.1981907093],"iteration":965,"passed_time":6.5513809,"remaining_time":0.2305869054},
{"learn":[0.1981840382],"iteration":966,"passed_time":6.555739091,"remaining_time":0.2237222234},
{"learn":[0.1977795434],"iteration":967,"passed_time":6.559538017,"remaining_time":0.216844232},
{"learn":[0.1971997623],"iteration":968,"passed_time":6.564368776,"remaining_time":0.2100056058},
{"learn":[0.1966917568],"iteration":969,"passed_time":6.568848157,"remaining_time":0.2031602523},
{"learn":[0.1962849411],"iteration":970,"passed_time":6.573326202,"remaining_time":0.1963197321},
{"learn":[0.1960051942],"iteration":971,"passed_time":6.577735675,"remaining_time":0.1894820976},
{"learn":[0.1956703324],"iteration":972,"passed_time":6.581494634,"remaining_time":0.182631403},
{"learn":[0.1953199268],"iteration":973,"passed_time":6.585786974,"remaining_time":0.175801295},
{"learn":[0.1949602163],"iteration":974,"passed_time":6.598160285,"remaining_time":0.169183597},
{"learn":[0.1949525181],"iteration":975,"passed_time":6.603646965,"remaining_time":0.1623847614},
{"learn":[0.1946160695],"iteration":976,"passed_time":6.608761428,"remaining_time":0.1555798494},
{"learn":[0.1942463463],"iteration":977,"passed_time":6.613514591,"remaining_time":0.1487702669},
{"learn":[0.1938657794],"iteration":978,"passed_time":6.618288289,"remaining_time":0.1419653259},
{"learn":[0.1935822009],"iteration":979,"passed_time":6.622129791,"remaining_time":0.1351455059},
{"learn":[0.193274117],"iteration":980,"passed_time":6.626321631,"remaining_time":0.1283385433},
{"learn":[0.1931065888],"iteration":981,"passed_time":6.630210933,"remaining_time":0.1215313613},
{"learn":[0.1926478156],"iteration":982,"passed_time":6.635706545,"remaining_time":0.1147578955},
{"learn":[0.1922401801],"iteration":983,"passed_time":6.639995429,"remaining_time":0.1079674053},
{"learn":[0.1919715],"iteration":984,"passed_time":6.644012977,"remaining_time":0.1011778626},
{"learn":[0.1916721622],"iteration":985,"passed_time":6.647819632,"remaining_time":0.09439094811},
{"learn":[0.1913430034],"iteration":986,"passed_time":6.651894646,"remaining_time":0.08761360729},
{"learn":[0.1908680518],"iteration":987,"passed_time":6.656915332,"remaining_time":0.08085322266},
{"learn":[0.19039907],"iteration":988,"passed_time":6.663222754,"remaining_time":0.07411066764},
{"learn":[0.1900093828],"iteration":989,"passed_time":6.666904289,"remaining_time":0.06734246757},
{"learn":[0.1897579517],"iteration":990,"passed_time":6.671235135,"remaining_time":0.06058639376},
{"learn":[0.189460842],"iteration":991,"passed_time":6.675045014,"remaining_time":0.05383100817},
{"learn":[0.1891305275],"iteration":992,"passed_time":6.679167515,"remaining_time":0.04708375892},
{"learn":[0.1886414268],"iteration":993,"passed_time":6.686339287,"remaining_time":0.0403601969},
{"learn":[0.1882056207],"iteration":994,"passed_time":6.690991633,"remaining_time":0.03362307353},
{"learn":[0.1878874321],"iteration":995,"passed_time":6.695143477,"remaining_time":0.02688812641},
{"learn":[0.1875978562],"iteration":996,"passed_time":6.717944558,"remaining_time":0.0202144771},
{"learn":[0.1871466422],"iteration":997,"passed_time":6.724475195,"remaining_time":0.01347590219},
{"learn":[0.1867300299],"iteration":998,"passed_time":6.73504026,"remaining_time":0.006741782042},
{"learn":[0.1863510342],"iteration":999,"passed_time":6.742693952,"remaining_time":0}
]}